{
"meta":{"test_sets":[],"test_metrics":[],"learn_metrics":[{"best_value":"Min","name":"Logloss"}],"launch_mode":"Train","parameters":"","iteration_count":1000,"learn_sets":["learn"],"name":"experiment"},
"iterations":[
{"learn":[0.5497068487],"iteration":0,"passed_time":0.01606117253,"remaining_time":16.04511135},
{"learn":[0.4470667291],"iteration":1,"passed_time":0.03137498469,"remaining_time":15.65611736},
{"learn":[0.3662697165],"iteration":2,"passed_time":0.04611697446,"remaining_time":15.32620785},
{"learn":[0.3089562965],"iteration":3,"passed_time":0.06293341764,"remaining_time":15.67042099},
{"learn":[0.270150174],"iteration":4,"passed_time":0.08081576456,"remaining_time":16.08233715},
{"learn":[0.2390179195],"iteration":5,"passed_time":0.0983095938,"remaining_time":16.28662271},
{"learn":[0.2177508002],"iteration":6,"passed_time":0.1139206122,"remaining_time":16.16045256},
{"learn":[0.2019643112],"iteration":7,"passed_time":0.1284151316,"remaining_time":15.92347632},
{"learn":[0.1891913522],"iteration":8,"passed_time":0.1437684242,"remaining_time":15.83050093},
{"learn":[0.1801865776],"iteration":9,"passed_time":0.1605950036,"remaining_time":15.89890536},
{"learn":[0.1728207268],"iteration":10,"passed_time":0.1776618948,"remaining_time":15.97341945},
{"learn":[0.1676282363],"iteration":11,"passed_time":0.1925198418,"remaining_time":15.85080031},
{"learn":[0.1628416437],"iteration":12,"passed_time":0.2079055987,"remaining_time":15.78483277},
{"learn":[0.1598481359],"iteration":13,"passed_time":0.223140619,"remaining_time":15.71547503},
{"learn":[0.1570066351],"iteration":14,"passed_time":0.2389316612,"remaining_time":15.68984575},
{"learn":[0.1547794233],"iteration":15,"passed_time":0.254812634,"remaining_time":15.67097699},
{"learn":[0.1534475851],"iteration":16,"passed_time":0.272043877,"remaining_time":15.73053712},
{"learn":[0.1522549807],"iteration":17,"passed_time":0.2875602972,"remaining_time":15.68801177},
{"learn":[0.1512444657],"iteration":18,"passed_time":0.3026876036,"remaining_time":15.6282389},
{"learn":[0.1503978457],"iteration":19,"passed_time":0.3174455451,"remaining_time":15.55483171},
{"learn":[0.1498115555],"iteration":20,"passed_time":0.3331105274,"remaining_time":15.52929554},
{"learn":[0.1489115017],"iteration":21,"passed_time":0.3491736793,"remaining_time":15.5223572},
{"learn":[0.1482408769],"iteration":22,"passed_time":0.3648626089,"remaining_time":15.49872908},
{"learn":[0.1478056779],"iteration":23,"passed_time":0.3817001607,"remaining_time":15.5224732},
{"learn":[0.1474759007],"iteration":24,"passed_time":0.3973265907,"remaining_time":15.49573704},
{"learn":[0.1470990157],"iteration":25,"passed_time":0.4137500289,"remaining_time":15.49971262},
{"learn":[0.1466755234],"iteration":26,"passed_time":0.4308860967,"remaining_time":15.52785823},
{"learn":[0.146445314],"iteration":27,"passed_time":0.4466968984,"remaining_time":15.50676376},
{"learn":[0.1460785884],"iteration":28,"passed_time":0.462575834,"remaining_time":15.48831499},
{"learn":[0.1458216763],"iteration":29,"passed_time":0.479508958,"remaining_time":15.50412298},
{"learn":[0.145640479],"iteration":30,"passed_time":0.4959835364,"remaining_time":15.50348538},
{"learn":[0.1455100575],"iteration":31,"passed_time":0.5105321992,"remaining_time":15.44359902},
{"learn":[0.1453041746],"iteration":32,"passed_time":0.5270882156,"remaining_time":15.44528195},
{"learn":[0.1451443962],"iteration":33,"passed_time":0.5426008648,"remaining_time":15.4162481},
{"learn":[0.1449979254],"iteration":34,"passed_time":0.5596949438,"remaining_time":15.43158916},
{"learn":[0.1448446847],"iteration":35,"passed_time":0.5747264232,"remaining_time":15.38989644},
{"learn":[0.1447146887],"iteration":36,"passed_time":0.5918203035,"remaining_time":15.40332304},
{"learn":[0.1446348174],"iteration":37,"passed_time":0.6074636566,"remaining_time":15.37842204},
{"learn":[0.1444666748],"iteration":38,"passed_time":0.6223981985,"remaining_time":15.33652997},
{"learn":[0.1443144196],"iteration":39,"passed_time":0.6396665235,"remaining_time":15.35199656},
{"learn":[0.1441668316],"iteration":40,"passed_time":0.6571366466,"remaining_time":15.37058644},
{"learn":[0.1440776368],"iteration":41,"passed_time":0.6727950075,"remaining_time":15.34613374},
{"learn":[0.1439760472],"iteration":42,"passed_time":0.6888918975,"remaining_time":15.33184991},
{"learn":[0.1438825911],"iteration":43,"passed_time":0.7041019092,"remaining_time":15.29821421},
{"learn":[0.1438037639],"iteration":44,"passed_time":0.7201558491,"remaining_time":15.28330746},
{"learn":[0.1437096755],"iteration":45,"passed_time":0.7354247341,"remaining_time":15.25206949},
{"learn":[0.1436293994],"iteration":46,"passed_time":0.7502167971,"remaining_time":15.21184271},
{"learn":[0.1435563854],"iteration":47,"passed_time":0.764695311,"remaining_time":15.166457},
{"learn":[0.1434964292],"iteration":48,"passed_time":0.7798097567,"remaining_time":15.13467507},
{"learn":[0.1434234835],"iteration":49,"passed_time":0.7955342665,"remaining_time":15.11515106},
{"learn":[0.1433205709],"iteration":50,"passed_time":0.8117374441,"remaining_time":15.10468303},
{"learn":[0.1432183378],"iteration":51,"passed_time":0.8270646487,"remaining_time":15.07802475},
{"learn":[0.1431449178],"iteration":52,"passed_time":0.8421332743,"remaining_time":15.04717379},
{"learn":[0.1430919653],"iteration":53,"passed_time":0.8557565966,"remaining_time":14.99158779},
{"learn":[0.1429966714],"iteration":54,"passed_time":0.8712393906,"remaining_time":14.9694768},
{"learn":[0.1429224694],"iteration":55,"passed_time":0.8864907498,"remaining_time":14.94370121},
{"learn":[0.142846188],"iteration":56,"passed_time":0.9014268187,"remaining_time":14.91307877},
{"learn":[0.1427623214],"iteration":57,"passed_time":0.9169635747,"remaining_time":14.89275323},
{"learn":[0.1427003433],"iteration":58,"passed_time":0.9323018054,"remaining_time":14.86942371},
{"learn":[0.1426368386],"iteration":59,"passed_time":0.9472651938,"remaining_time":14.84048804},
{"learn":[0.1425920204],"iteration":60,"passed_time":0.9637983098,"remaining_time":14.83617398},
{"learn":[0.1425026319],"iteration":61,"passed_time":0.9814298008,"remaining_time":14.84808311},
{"learn":[0.1424437456],"iteration":62,"passed_time":0.9964088708,"remaining_time":14.81960495},
{"learn":[0.1423650864],"iteration":63,"passed_time":1.012683954,"remaining_time":14.81050283},
{"learn":[0.1423203559],"iteration":64,"passed_time":1.028269712,"remaining_time":14.79126432},
{"learn":[0.142281543],"iteration":65,"passed_time":1.042966151,"remaining_time":14.75955129},
{"learn":[0.1422210147],"iteration":66,"passed_time":1.058985711,"remaining_time":14.74677116},
{"learn":[0.1421555853],"iteration":67,"passed_time":1.077158845,"remaining_time":14.7634124},
{"learn":[0.1421244498],"iteration":68,"passed_time":1.093088567,"remaining_time":14.74877473},
{"learn":[0.142039313],"iteration":69,"passed_time":1.110433725,"remaining_time":14.7529052},
{"learn":[0.1419679362],"iteration":70,"passed_time":1.126882452,"remaining_time":14.74470137},
{"learn":[0.1419291506],"iteration":71,"passed_time":1.141668537,"remaining_time":14.71483892},
{"learn":[0.1418790169],"iteration":72,"passed_time":1.15674665,"remaining_time":14.68909787},
{"learn":[0.1418270643],"iteration":73,"passed_time":1.172384232,"remaining_time":14.67064594},
{"learn":[0.1417936367],"iteration":74,"passed_time":1.187876353,"remaining_time":14.65047502},
{"learn":[0.1417505296],"iteration":75,"passed_time":1.203067617,"remaining_time":14.62676945},
{"learn":[0.1417016881],"iteration":76,"passed_time":1.218736588,"remaining_time":14.60901131},
{"learn":[0.1416752697],"iteration":77,"passed_time":1.234367337,"remaining_time":14.59085493},
{"learn":[0.1416236091],"iteration":78,"passed_time":1.250467451,"remaining_time":14.57823445},
{"learn":[0.1415881048],"iteration":79,"passed_time":1.265352392,"remaining_time":14.55155251},
{"learn":[0.1415282832],"iteration":80,"passed_time":1.281100285,"remaining_time":14.53495261},
{"learn":[0.1414993872],"iteration":81,"passed_time":1.295956673,"remaining_time":14.508393},
{"learn":[0.141463101],"iteration":82,"passed_time":1.312846573,"remaining_time":14.50458202},
{"learn":[0.1414283835],"iteration":83,"passed_time":1.328404408,"remaining_time":14.48593379},
{"learn":[0.1413712503],"iteration":84,"passed_time":1.344204087,"remaining_time":14.46996164},
{"learn":[0.1413203609],"iteration":85,"passed_time":1.35914757,"remaining_time":14.44489394},
{"learn":[0.1412612469],"iteration":86,"passed_time":1.374627759,"remaining_time":14.42569131},
{"learn":[0.1412163796],"iteration":87,"passed_time":1.390748982,"remaining_time":14.41321672},
{"learn":[0.1411865696],"iteration":88,"passed_time":1.406611913,"remaining_time":14.39801632},
{"learn":[0.141133063],"iteration":89,"passed_time":1.42233485,"remaining_time":14.3813857},
{"learn":[0.1410967227],"iteration":90,"passed_time":1.436262786,"remaining_time":14.34684476},
{"learn":[0.1410499424],"iteration":91,"passed_time":1.451352638,"remaining_time":14.32421952},
{"learn":[0.1410050913],"iteration":92,"passed_time":1.466662177,"remaining_time":14.30389887},
{"learn":[0.1409511084],"iteration":93,"passed_time":1.481982778,"remaining_time":14.28379145},
{"learn":[0.1409011638],"iteration":94,"passed_time":1.496817188,"remaining_time":14.25915321},
{"learn":[0.140850078],"iteration":95,"passed_time":1.511752691,"remaining_time":14.23567118},
{"learn":[0.1408058621],"iteration":96,"passed_time":1.528820609,"remaining_time":14.2322166},
{"learn":[0.1407526897],"iteration":97,"passed_time":1.544964461,"remaining_time":14.21997902},
{"learn":[0.1406996943],"iteration":98,"passed_time":1.561503477,"remaining_time":14.21125891},
{"learn":[0.1406554445],"iteration":99,"passed_time":1.576793243,"remaining_time":14.19113918},
{"learn":[0.1406221279],"iteration":100,"passed_time":1.592426589,"remaining_time":14.1741733},
{"learn":[0.1405845163],"iteration":101,"passed_time":1.607347877,"remaining_time":14.15096464},
{"learn":[0.1405389817],"iteration":102,"passed_time":1.622780887,"remaining_time":14.13237336},
{"learn":[0.1405174038],"iteration":103,"passed_time":1.637825904,"remaining_time":14.11050009},
{"learn":[0.1404749252],"iteration":104,"passed_time":1.65265492,"remaining_time":14.08691574},
{"learn":[0.140433872],"iteration":105,"passed_time":1.667791695,"remaining_time":14.06609222},
{"learn":[0.1403920134],"iteration":106,"passed_time":1.683745724,"remaining_time":14.05219562},
{"learn":[0.1403616416],"iteration":107,"passed_time":1.698165713,"remaining_time":14.02559089},
{"learn":[0.1403149376],"iteration":108,"passed_time":1.71279876,"remaining_time":14.00095133},
{"learn":[0.1402628341],"iteration":109,"passed_time":1.728345673,"remaining_time":13.98388772},
{"learn":[0.1402188971],"iteration":110,"passed_time":1.743466692,"remaining_time":13.96344045},
{"learn":[0.1401862307],"iteration":111,"passed_time":1.758390126,"remaining_time":13.94152172},
{"learn":[0.1401480643],"iteration":112,"passed_time":1.775171978,"remaining_time":13.93431455},
{"learn":[0.1401005336],"iteration":113,"passed_time":1.789612522,"remaining_time":13.90874293},
{"learn":[0.14007511],"iteration":114,"passed_time":1.805117726,"remaining_time":13.89155815},
{"learn":[0.1400042734],"iteration":115,"passed_time":1.821278529,"remaining_time":13.87939844},
{"learn":[0.1399741636],"iteration":116,"passed_time":1.83627848,"remaining_time":13.85840939},
{"learn":[0.1399128021],"iteration":117,"passed_time":1.851267526,"remaining_time":13.83744032},
{"learn":[0.139866065],"iteration":118,"passed_time":1.86720512,"remaining_time":13.82359421},
{"learn":[0.1398180801],"iteration":119,"passed_time":1.882260482,"remaining_time":13.80324354},
{"learn":[0.139774468],"iteration":120,"passed_time":1.897606936,"remaining_time":13.78509501},
{"learn":[0.1397305297],"iteration":121,"passed_time":1.912552028,"remaining_time":13.76410394},
{"learn":[0.1396857427],"iteration":122,"passed_time":1.927724581,"remaining_time":13.74483299},
{"learn":[0.1396458348],"iteration":123,"passed_time":1.944077002,"remaining_time":13.73396334},
{"learn":[0.1395891113],"iteration":124,"passed_time":1.963090827,"remaining_time":13.74163579},
{"learn":[0.1395546266],"iteration":125,"passed_time":1.978665432,"remaining_time":13.72502847},
{"learn":[0.1395202687],"iteration":126,"passed_time":1.993675229,"remaining_time":13.70455492},
{"learn":[0.1394862806],"iteration":127,"passed_time":2.008475827,"remaining_time":13.68274157},
{"learn":[0.1394444887],"iteration":128,"passed_time":2.023941526,"remaining_time":13.66552767},
{"learn":[0.1393982826],"iteration":129,"passed_time":2.03966533,"remaining_time":13.65006798},
{"learn":[0.139370387],"iteration":130,"passed_time":2.054135911,"remaining_time":13.62629089},
{"learn":[0.1393343235],"iteration":131,"passed_time":2.070375285,"remaining_time":13.61428596},
{"learn":[0.1392932603],"iteration":132,"passed_time":2.085421796,"remaining_time":13.59444133},
{"learn":[0.1392544253],"iteration":133,"passed_time":2.101248239,"remaining_time":13.57970877},
{"learn":[0.1392260119],"iteration":134,"passed_time":2.116897136,"remaining_time":13.56382239},
{"learn":[0.1391775599],"iteration":135,"passed_time":2.131623888,"remaining_time":13.54208117},
{"learn":[0.1391544996],"iteration":136,"passed_time":2.146985338,"remaining_time":13.52444049},
{"learn":[0.1391117395],"iteration":137,"passed_time":2.162140658,"remaining_time":13.50554527},
{"learn":[0.1390762309],"iteration":138,"passed_time":2.177267292,"remaining_time":13.48652617},
{"learn":[0.1390515289],"iteration":139,"passed_time":2.192310854,"remaining_time":13.46705239},
{"learn":[0.1390244768],"iteration":140,"passed_time":2.208309516,"remaining_time":13.4534601},
{"learn":[0.1389907898],"iteration":141,"passed_time":2.222972616,"remaining_time":13.43176411},
{"learn":[0.1389449636],"iteration":142,"passed_time":2.239402531,"remaining_time":13.42075503},
{"learn":[0.1389231812],"iteration":143,"passed_time":2.252979499,"remaining_time":13.39271147},
{"learn":[0.1388787945],"iteration":144,"passed_time":2.268787305,"remaining_time":13.37802169},
{"learn":[0.1388387661],"iteration":145,"passed_time":2.283786928,"remaining_time":13.35858929},
{"learn":[0.1387875012],"iteration":146,"passed_time":2.299368533,"remaining_time":13.34259427},
{"learn":[0.1387456718],"iteration":147,"passed_time":2.31457574,"remaining_time":13.32444953},
{"learn":[0.1386957146],"iteration":148,"passed_time":2.329454314,"remaining_time":13.30446725},
{"learn":[0.1386683334],"iteration":149,"passed_time":2.345054921,"remaining_time":13.28864455},
{"learn":[0.1386239813],"iteration":150,"passed_time":2.360906653,"remaining_time":13.27423674},
{"learn":[0.1385769261],"iteration":151,"passed_time":2.37671223,"remaining_time":13.25955244},
{"learn":[0.1385421344],"iteration":152,"passed_time":2.391384696,"remaining_time":13.23858064},
{"learn":[0.1384998369],"iteration":153,"passed_time":2.406607817,"remaining_time":13.22071567},
{"learn":[0.1384559069],"iteration":154,"passed_time":2.422223295,"remaining_time":13.20502377},
{"learn":[0.1384179348],"iteration":155,"passed_time":2.436968863,"remaining_time":13.18462641},
{"learn":[0.1383823405],"iteration":156,"passed_time":2.452507193,"remaining_time":13.16855773},
{"learn":[0.1383387989],"iteration":157,"passed_time":2.468250007,"remaining_time":13.15358548},
{"learn":[0.1382834714],"iteration":158,"passed_time":2.483370465,"remaining_time":13.13531171},
{"learn":[0.1382347523],"iteration":159,"passed_time":2.498299987,"remaining_time":13.11607493},
{"learn":[0.1382125829],"iteration":160,"passed_time":2.513807137,"remaining_time":13.09990179},
{"learn":[0.1381728553],"iteration":161,"passed_time":2.530027472,"remaining_time":13.08742606},
{"learn":[0.1381276346],"iteration":162,"passed_time":2.546120375,"remaining_time":13.07425002},
{"learn":[0.1380880432],"iteration":163,"passed_time":2.562185312,"remaining_time":13.06089586},
{"learn":[0.1380470027],"iteration":164,"passed_time":2.577276036,"remaining_time":13.04257873},
{"learn":[0.13801279],"iteration":165,"passed_time":2.592302971,"remaining_time":13.02397999},
{"learn":[0.1379819084],"iteration":166,"passed_time":2.607910721,"remaining_time":13.00832114},
{"learn":[0.1379357217],"iteration":167,"passed_time":2.622939136,"remaining_time":12.98979382},
{"learn":[0.1379201076],"iteration":168,"passed_time":2.637205162,"remaining_time":12.96755911},
{"learn":[0.1378914541],"iteration":169,"passed_time":2.65193209,"remaining_time":12.94766844},
{"learn":[0.1378756044],"iteration":170,"passed_time":2.66713789,"remaining_time":12.93015971},
{"learn":[0.137831744],"iteration":171,"passed_time":2.682508774,"remaining_time":12.91347247},
{"learn":[0.1377946757],"iteration":172,"passed_time":2.698075707,"remaining_time":12.89773763},
{"learn":[0.1377536741],"iteration":173,"passed_time":2.714127351,"remaining_time":12.8843057},
{"learn":[0.1377201467],"iteration":174,"passed_time":2.729195293,"remaining_time":12.86620638},
{"learn":[0.137703844],"iteration":175,"passed_time":2.743520502,"remaining_time":12.84466417},
{"learn":[0.1376541195],"iteration":176,"passed_time":2.759783168,"remaining_time":12.83221213},
{"learn":[0.1376149144],"iteration":177,"passed_time":2.775652343,"remaining_time":12.81790014},
{"learn":[0.1375765957],"iteration":178,"passed_time":2.790425517,"remaining_time":12.79854385},
{"learn":[0.1375380233],"iteration":179,"passed_time":2.813327907,"remaining_time":12.81627158},
{"learn":[0.1375042791],"iteration":180,"passed_time":2.82786679,"remaining_time":12.79570664},
{"learn":[0.1374729436],"iteration":181,"passed_time":2.84171946,"remaining_time":12.77212373},
{"learn":[0.1374455689],"iteration":182,"passed_time":2.85674709,"remaining_time":12.75389275},
{"learn":[0.1374131474],"iteration":183,"passed_time":2.87149489,"remaining_time":12.7344556},
{"learn":[0.137388867],"iteration":184,"passed_time":2.885797865,"remaining_time":12.71310952},
{"learn":[0.1373361575],"iteration":185,"passed_time":2.902132842,"remaining_time":12.7007319},
{"learn":[0.1372943021],"iteration":186,"passed_time":2.917627087,"remaining_time":12.6846568},
{"learn":[0.1372523254],"iteration":187,"passed_time":2.935783663,"remaining_time":12.68008688},
{"learn":[0.1372203321],"iteration":188,"passed_time":2.951528025,"remaining_time":12.66502237},
{"learn":[0.1371802055],"iteration":189,"passed_time":2.968218961,"remaining_time":12.6539861},
{"learn":[0.1371459488],"iteration":190,"passed_time":2.983610437,"remaining_time":12.63738662},
{"learn":[0.1371214672],"iteration":191,"passed_time":2.998063206,"remaining_time":12.61684933},
{"learn":[0.1370884523],"iteration":192,"passed_time":3.012769375,"remaining_time":12.59743464},
{"learn":[0.1370530185],"iteration":193,"passed_time":3.027084543,"remaining_time":12.57644403},
{"learn":[0.137010973],"iteration":194,"passed_time":3.042105797,"remaining_time":12.55843675},
{"learn":[0.1369776259],"iteration":195,"passed_time":3.058320489,"remaining_time":12.54535547},
{"learn":[0.1369502761],"iteration":196,"passed_time":3.073783331,"remaining_time":12.52917774},
{"learn":[0.1369160603],"iteration":197,"passed_time":3.090430456,"remaining_time":12.51780417},
{"learn":[0.1368791619],"iteration":198,"passed_time":3.10598856,"remaining_time":12.50199415},
{"learn":[0.1368351313],"iteration":199,"passed_time":3.121560304,"remaining_time":12.48624122},
{"learn":[0.136789737],"iteration":200,"passed_time":3.136820329,"remaining_time":12.46925096},
{"learn":[0.1367767656],"iteration":201,"passed_time":3.150508418,"remaining_time":12.44606791},
{"learn":[0.1367417391],"iteration":202,"passed_time":3.165856582,"remaining_time":12.42949604},
{"learn":[0.1366973635],"iteration":203,"passed_time":3.181868717,"remaining_time":12.41552695},
{"learn":[0.1366517743],"iteration":204,"passed_time":3.198023288,"remaining_time":12.40209031},
{"learn":[0.136636622],"iteration":205,"passed_time":3.213333774,"remaining_time":12.38537387},
{"learn":[0.1366009781],"iteration":206,"passed_time":3.228917165,"remaining_time":12.36971648},
{"learn":[0.1365666912],"iteration":207,"passed_time":3.243621438,"remaining_time":12.3507124},
{"learn":[0.136541114],"iteration":208,"passed_time":3.258627077,"remaining_time":12.33289004},
{"learn":[0.1365173373],"iteration":209,"passed_time":3.273602173,"remaining_time":12.3149796},
{"learn":[0.1364783183],"iteration":210,"passed_time":3.289883412,"remaining_time":12.3019811},
{"learn":[0.1364556202],"iteration":211,"passed_time":3.305776609,"remaining_time":12.28750928},
{"learn":[0.1364198509],"iteration":212,"passed_time":3.321151061,"remaining_time":12.27110744},
{"learn":[0.1363795448],"iteration":213,"passed_time":3.335717775,"remaining_time":12.25174846},
{"learn":[0.136347921],"iteration":214,"passed_time":3.349885443,"remaining_time":12.23097708},
{"learn":[0.1363312176],"iteration":215,"passed_time":3.365578231,"remaining_time":12.21580247},
{"learn":[0.1362953471],"iteration":216,"passed_time":3.380046982,"remaining_time":12.19620639},
{"learn":[0.136272598],"iteration":217,"passed_time":3.394634812,"remaining_time":12.17708451},
{"learn":[0.1362449717],"iteration":218,"passed_time":3.409640154,"remaining_time":12.15949297},
{"learn":[0.1362044057],"iteration":219,"passed_time":3.425408794,"remaining_time":12.14463118},
{"learn":[0.1361660061],"iteration":220,"passed_time":3.440936497,"remaining_time":12.12891191},
{"learn":[0.1361415924],"iteration":221,"passed_time":3.456012559,"remaining_time":12.11161158},
{"learn":[0.1361047435],"iteration":222,"passed_time":3.471218332,"remaining_time":12.09478316},
{"learn":[0.1360744704],"iteration":223,"passed_time":3.485674592,"remaining_time":12.07537269},
{"learn":[0.1360286175],"iteration":224,"passed_time":3.501841563,"remaining_time":12.06189872},
{"learn":[0.1360005966],"iteration":225,"passed_time":3.517327645,"remaining_time":12.04606902},
{"learn":[0.1359732102],"iteration":226,"passed_time":3.532409094,"remaining_time":12.02886445},
{"learn":[0.1359289005],"iteration":227,"passed_time":3.548118773,"remaining_time":12.01380567},
{"learn":[0.1358946796],"iteration":228,"passed_time":3.563710974,"remaining_time":11.99834568},
{"learn":[0.1358565269],"iteration":229,"passed_time":3.579106389,"remaining_time":11.98222574},
{"learn":[0.1358354269],"iteration":230,"passed_time":3.594500839,"remaining_time":11.96610885},
{"learn":[0.1357913414],"iteration":231,"passed_time":3.609611591,"remaining_time":11.94905906},
{"learn":[0.1357453913],"iteration":232,"passed_time":3.629391767,"remaining_time":11.94739693},
{"learn":[0.1357092106],"iteration":233,"passed_time":3.645357037,"remaining_time":11.93309184},
{"learn":[0.1356634123],"iteration":234,"passed_time":3.659816375,"remaining_time":11.91387033},
{"learn":[0.1356323072],"iteration":235,"passed_time":3.674502621,"remaining_time":11.89542374},
{"learn":[0.135602585],"iteration":236,"passed_time":3.68899508,"remaining_time":11.876385},
{"learn":[0.1355603939],"iteration":237,"passed_time":3.703761525,"remaining_time":11.85826169},
{"learn":[0.1355352108],"iteration":238,"passed_time":3.71953828,"remaining_time":11.84338339},
{"learn":[0.1355016077],"iteration":239,"passed_time":3.734579308,"remaining_time":11.82616781},
{"learn":[0.1354937326],"iteration":240,"passed_time":3.748819953,"remaining_time":11.80644956},
{"learn":[0.1354397232],"iteration":241,"passed_time":3.764607527,"remaining_time":11.79162192},
{"learn":[0.1354227068],"iteration":242,"passed_time":3.779458986,"remaining_time":11.77387018},
{"learn":[0.1353994779],"iteration":243,"passed_time":3.793873794,"remaining_time":11.75478929},
{"learn":[0.1353674309],"iteration":244,"passed_time":3.808219396,"remaining_time":11.73553324},
{"learn":[0.1353322858],"iteration":245,"passed_time":3.823641254,"remaining_time":11.71961588},
{"learn":[0.135287754],"iteration":246,"passed_time":3.838707178,"remaining_time":11.70261743},
{"learn":[0.1352604162],"iteration":247,"passed_time":3.852726071,"remaining_time":11.6824597},
{"learn":[0.1352248548],"iteration":248,"passed_time":3.867920927,"remaining_time":11.66589806},
{"learn":[0.1351949068],"iteration":249,"passed_time":3.882262852,"remaining_time":11.64678855},
{"learn":[0.1351578338],"iteration":250,"passed_time":3.897500555,"remaining_time":11.6303901},
{"learn":[0.1351278031],"iteration":251,"passed_time":3.913331858,"remaining_time":11.61576282},
{"learn":[0.1350892085],"iteration":252,"passed_time":3.930154948,"remaining_time":11.60405433},
{"learn":[0.1350642484],"iteration":253,"passed_time":3.946544816,"remaining_time":11.5910332},
{"learn":[0.1350384145],"iteration":254,"passed_time":3.962271895,"remaining_time":11.57604926},
{"learn":[0.1350153262],"iteration":255,"passed_time":3.976660179,"remaining_time":11.55716864},
{"learn":[0.1349933573],"iteration":256,"passed_time":3.991807149,"remaining_time":11.54051639},
{"learn":[0.1349582397],"iteration":257,"passed_time":4.007100662,"remaining_time":11.52429725},
{"learn":[0.1349261157],"iteration":258,"passed_time":4.022784188,"remaining_time":11.50920109},
{"learn":[0.1348968685],"iteration":259,"passed_time":4.037913099,"remaining_time":11.4925219},
{"learn":[0.1348718032],"iteration":260,"passed_time":4.055119336,"remaining_time":11.48173636},
{"learn":[0.1348476517],"iteration":261,"passed_time":4.070416958,"remaining_time":11.46552563},
{"learn":[0.1348058898],"iteration":262,"passed_time":4.08540989,"remaining_time":11.44846802},
{"learn":[0.1347633413],"iteration":263,"passed_time":4.100861774,"remaining_time":11.43270555},
{"learn":[0.1347369249],"iteration":264,"passed_time":4.115579818,"remaining_time":11.41491006},
{"learn":[0.1347093193],"iteration":265,"passed_time":4.13079777,"remaining_time":11.39851716},
{"learn":[0.1346700015],"iteration":266,"passed_time":4.146600408,"remaining_time":11.3837382},
{"learn":[0.1346361946],"iteration":267,"passed_time":4.161378616,"remaining_time":11.36615353},
{"learn":[0.1346032839],"iteration":268,"passed_time":4.175996338,"remaining_time":11.34815362},
{"learn":[0.1345776074],"iteration":269,"passed_time":4.192250536,"remaining_time":11.3346033},
{"learn":[0.1345478673],"iteration":270,"passed_time":4.207344453,"remaining_time":11.31791183},
{"learn":[0.13450762],"iteration":271,"passed_time":4.222389031,"remaining_time":11.30110005},
{"learn":[0.1344764053],"iteration":272,"passed_time":4.238455792,"remaining_time":11.2870233},
{"learn":[0.1344521477],"iteration":273,"passed_time":4.253534902,"remaining_time":11.27031511},
{"learn":[0.1344145853],"iteration":274,"passed_time":4.268249279,"remaining_time":11.25265719},
{"learn":[0.1343826861],"iteration":275,"passed_time":4.282726877,"remaining_time":11.23439949},
{"learn":[0.1343533158],"iteration":276,"passed_time":4.298140994,"remaining_time":11.2186135},
{"learn":[0.1343062624],"iteration":277,"passed_time":4.313274513,"remaining_time":11.20210143},
{"learn":[0.1342635241],"iteration":278,"passed_time":4.329651192,"remaining_time":11.18881186},
{"learn":[0.1342337632],"iteration":279,"passed_time":4.345681181,"remaining_time":11.17460875},
{"learn":[0.134191813],"iteration":280,"passed_time":4.360897021,"remaining_time":11.15830946},
{"learn":[0.1341610221],"iteration":281,"passed_time":4.375311433,"remaining_time":11.13997734},
{"learn":[0.1341263104],"iteration":282,"passed_time":4.391191376,"remaining_time":11.12538592},
{"learn":[0.1340971848],"iteration":283,"passed_time":4.406294812,"remaining_time":11.10882776},
{"learn":[0.1340654492],"iteration":284,"passed_time":4.421769373,"remaining_time":11.09321088},
{"learn":[0.1340230872],"iteration":285,"passed_time":4.436723787,"remaining_time":11.07629645},
{"learn":[0.1339816622],"iteration":286,"passed_time":4.453545595,"remaining_time":11.06403488},
{"learn":[0.1339661798],"iteration":287,"passed_time":4.467448227,"remaining_time":11.04452478},
{"learn":[0.1339335364],"iteration":288,"passed_time":4.483294064,"remaining_time":11.02983418},
{"learn":[0.1339026464],"iteration":289,"passed_time":4.498968551,"remaining_time":11.01471611},
{"learn":[0.1338520137],"iteration":290,"passed_time":4.515473692,"remaining_time":11.00161803},
{"learn":[0.1338286776],"iteration":291,"passed_time":4.530753996,"remaining_time":10.98552681},
{"learn":[0.1337994304],"iteration":292,"passed_time":4.547154366,"remaining_time":10.97214381},
{"learn":[0.133782423],"iteration":293,"passed_time":4.563587224,"remaining_time":10.9588183},
{"learn":[0.1337499727],"iteration":294,"passed_time":4.579877531,"remaining_time":10.94513105},
{"learn":[0.1336998135],"iteration":295,"passed_time":4.595960743,"remaining_time":10.93093366},
{"learn":[0.1336655849],"iteration":296,"passed_time":4.61193755,"remaining_time":10.91647171},
{"learn":[0.1336336831],"iteration":297,"passed_time":4.627283006,"remaining_time":10.90051232},
{"learn":[0.1336038155],"iteration":298,"passed_time":4.64332994,"remaining_time":10.88620163},
{"learn":[0.1335966495],"iteration":299,"passed_time":4.656327385,"remaining_time":10.8647639},
{"learn":[0.1335764922],"iteration":300,"passed_time":4.672574808,"remaining_time":10.85092954},
{"learn":[0.1335543712],"iteration":301,"passed_time":4.687636569,"remaining_time":10.83433882},
{"learn":[0.1335170486],"iteration":302,"passed_time":4.703244853,"remaining_time":10.81901539},
{"learn":[0.1334877271],"iteration":303,"passed_time":4.71954554,"remaining_time":10.80527532},
{"learn":[0.1334505807],"iteration":304,"passed_time":4.735108557,"remaining_time":10.78983753},
{"learn":[0.1334077835],"iteration":305,"passed_time":4.751103434,"remaining_time":10.77537838},
{"learn":[0.1333759156],"iteration":306,"passed_time":4.767680523,"remaining_time":10.76222346},
{"learn":[0.1333473042],"iteration":307,"passed_time":4.783132325,"remaining_time":10.74651808},
{"learn":[0.133327937],"iteration":308,"passed_time":4.797618373,"remaining_time":10.72865468},
{"learn":[0.1332992589],"iteration":309,"passed_time":4.812001798,"remaining_time":10.71058465},
{"learn":[0.1332759184],"iteration":310,"passed_time":4.826195603,"remaining_time":10.69211823},
{"learn":[0.1332411225],"iteration":311,"passed_time":4.841175945,"remaining_time":10.67541362},
{"learn":[0.1332046733],"iteration":312,"passed_time":4.857143114,"remaining_time":10.660886},
{"learn":[0.1331619255],"iteration":313,"passed_time":4.872962909,"remaining_time":10.64602725},
{"learn":[0.1331378269],"iteration":314,"passed_time":4.887335196,"remaining_time":10.62801463},
{"learn":[0.1331229826],"iteration":315,"passed_time":4.902416388,"remaining_time":10.61155952},
{"learn":[0.1331043353],"iteration":316,"passed_time":4.917278844,"remaining_time":10.5946418},
{"learn":[0.1330580815],"iteration":317,"passed_time":4.933505409,"remaining_time":10.58066254},
{"learn":[0.1330228697],"iteration":318,"passed_time":4.950953285,"remaining_time":10.56927645},
{"learn":[0.1329833163],"iteration":319,"passed_time":4.967027643,"remaining_time":10.55493374},
{"learn":[0.1329598003],"iteration":320,"passed_time":4.982787334,"remaining_time":10.53991464},
{"learn":[0.1329338402],"iteration":321,"passed_time":4.998076957,"remaining_time":10.52390117},
{"learn":[0.1328990441],"iteration":322,"passed_time":5.012930379,"remaining_time":10.50697792},
{"learn":[0.1328697412],"iteration":323,"passed_time":5.02788568,"remaining_time":10.49028},
{"learn":[0.1328397275],"iteration":324,"passed_time":5.044482422,"remaining_time":10.47700195},
{"learn":[0.1328145939],"iteration":325,"passed_time":5.059985059,"remaining_time":10.4614415},
{"learn":[0.132772646],"iteration":326,"passed_time":5.074418222,"remaining_time":10.44368032},
{"learn":[0.132743971],"iteration":327,"passed_time":5.089809268,"remaining_time":10.42790191},
{"learn":[0.1327278626],"iteration":328,"passed_time":5.104300385,"remaining_time":10.41029045},
{"learn":[0.1326908697],"iteration":329,"passed_time":5.119656602,"remaining_time":10.39445431},
{"learn":[0.1326740242],"iteration":330,"passed_time":5.13387042,"remaining_time":10.37631212},
{"learn":[0.1326369581],"iteration":331,"passed_time":5.149630072,"remaining_time":10.36130388},
{"learn":[0.1326128648],"iteration":332,"passed_time":5.164313299,"remaining_time":10.34413505},
{"learn":[0.132578],"iteration":333,"passed_time":5.181343731,"remaining_time":10.33166145},
{"learn":[0.1325382138],"iteration":334,"passed_time":5.196339374,"remaining_time":10.31512144},
{"learn":[0.1325265247],"iteration":335,"passed_time":5.210243696,"remaining_time":10.29643397},
{"learn":[0.1324866149],"iteration":336,"passed_time":5.226448212,"remaining_time":10.28230019},
{"learn":[0.13245544],"iteration":337,"passed_time":5.241561999,"remaining_time":10.26601788},
{"learn":[0.1324178698],"iteration":338,"passed_time":5.256761,"remaining_time":10.24990862},
{"learn":[0.1323908113],"iteration":339,"passed_time":5.271686728,"remaining_time":10.23327424},
{"learn":[0.1323517626],"iteration":340,"passed_time":5.288233542,"remaining_time":10.21978271},
{"learn":[0.1323140028],"iteration":341,"passed_time":5.303420457,"remaining_time":10.2036569},
{"learn":[0.1322822018],"iteration":342,"passed_time":5.319176214,"remaining_time":10.18862616},
{"learn":[0.1322502659],"iteration":343,"passed_time":5.334309762,"remaining_time":10.17240466},
{"learn":[0.132208509],"iteration":344,"passed_time":5.349574062,"remaining_time":10.15643771},
{"learn":[0.1321781413],"iteration":345,"passed_time":5.363665026,"remaining_time":10.13825701},
{"learn":[0.1321512408],"iteration":346,"passed_time":5.379918167,"remaining_time":10.12416877},
{"learn":[0.1321164663],"iteration":347,"passed_time":5.396639319,"remaining_time":10.11094493},
{"learn":[0.1320883493],"iteration":348,"passed_time":5.410808338,"remaining_time":10.09294048},
{"learn":[0.132067268],"iteration":349,"passed_time":5.425386999,"remaining_time":10.07571871},
{"learn":[0.1320427827],"iteration":350,"passed_time":5.440712873,"remaining_time":10.0598936},
{"learn":[0.1320145159],"iteration":351,"passed_time":5.456825707,"remaining_time":10.04552005},
{"learn":[0.1319775436],"iteration":352,"passed_time":5.471674473,"remaining_time":10.02881978},
{"learn":[0.1319436161],"iteration":353,"passed_time":5.487691398,"remaining_time":10.0142617},
{"learn":[0.1319356758],"iteration":354,"passed_time":5.502071268,"remaining_time":9.996721036},
{"learn":[0.1319215664],"iteration":355,"passed_time":5.516734465,"remaining_time":9.979710661},
{"learn":[0.1318885665],"iteration":356,"passed_time":5.532567297,"remaining_time":9.964820089},
{"learn":[0.1318599045],"iteration":357,"passed_time":5.54922323,"remaining_time":9.951400318},
{"learn":[0.1318216528],"iteration":358,"passed_time":5.56611624,"remaining_time":9.938385821},
{"learn":[0.1317966363],"iteration":359,"passed_time":5.581167143,"remaining_time":9.922074921},
{"learn":[0.1317702618],"iteration":360,"passed_time":5.597059236,"remaining_time":9.907259978},
{"learn":[0.1317388845],"iteration":361,"passed_time":5.613098235,"remaining_time":9.892697994},
{"learn":[0.1317041355],"iteration":362,"passed_time":5.628300291,"remaining_time":9.876659188},
{"learn":[0.1316679251],"iteration":363,"passed_time":5.643479646,"remaining_time":9.860585316},
{"learn":[0.1316302626],"iteration":364,"passed_time":5.659653578,"remaining_time":9.846246636},
{"learn":[0.1316048591],"iteration":365,"passed_time":5.675329199,"remaining_time":9.831034733},
{"learn":[0.1315785606],"iteration":366,"passed_time":5.690582251,"remaining_time":9.815091458},
{"learn":[0.1315407889],"iteration":367,"passed_time":5.706393321,"remaining_time":9.800110268},
{"learn":[0.1315140081],"iteration":368,"passed_time":5.721758796,"remaining_time":9.784362603},
{"learn":[0.1314929546],"iteration":369,"passed_time":5.737249207,"remaining_time":9.76882973},
{"learn":[0.1314740554],"iteration":370,"passed_time":5.752838653,"remaining_time":9.753464993},
{"learn":[0.1314334214],"iteration":371,"passed_time":5.76790096,"remaining_time":9.737209148},
{"learn":[0.131390775],"iteration":372,"passed_time":5.783445682,"remaining_time":9.721770623},
{"learn":[0.1313573986],"iteration":373,"passed_time":5.798052737,"remaining_time":9.704762069},
{"learn":[0.131335661],"iteration":374,"passed_time":5.81354432,"remaining_time":9.689240533},
{"learn":[0.1313072183],"iteration":375,"passed_time":5.828596166,"remaining_time":9.672989381},
{"learn":[0.1312843267],"iteration":376,"passed_time":5.843441912,"remaining_time":9.656404009},
{"learn":[0.1312567281],"iteration":377,"passed_time":5.857614034,"remaining_time":9.63871939},
{"learn":[0.1312179249],"iteration":378,"passed_time":5.873143028,"remaining_time":9.623276571},
{"learn":[0.1311859158],"iteration":379,"passed_time":5.889281406,"remaining_time":9.608827558},
{"learn":[0.1311585493],"iteration":380,"passed_time":5.904355733,"remaining_time":9.592640942},
{"learn":[0.1311302377],"iteration":381,"passed_time":5.920315668,"remaining_time":9.577892887},
{"learn":[0.1311001162],"iteration":382,"passed_time":5.937143048,"remaining_time":9.564535929},
{"learn":[0.1310814812],"iteration":383,"passed_time":5.951512153,"remaining_time":9.547217412},
{"learn":[0.1310426501],"iteration":384,"passed_time":5.966480754,"remaining_time":9.530871853},
{"learn":[0.1310159586],"iteration":385,"passed_time":5.982479549,"remaining_time":9.516172133},
{"learn":[0.1309817975],"iteration":386,"passed_time":5.997168069,"remaining_time":9.499390248},
{"learn":[0.1309603706],"iteration":387,"passed_time":6.011884379,"remaining_time":9.482662989},
{"learn":[0.1309258237],"iteration":388,"passed_time":6.029196458,"remaining_time":9.470023228},
{"learn":[0.1308873564],"iteration":389,"passed_time":6.045390096,"remaining_time":9.45561015},
{"learn":[0.1308605668],"iteration":390,"passed_time":6.060646357,"remaining_time":9.439727958},
{"learn":[0.1308386709],"iteration":391,"passed_time":6.07574105,"remaining_time":9.423598364},
{"learn":[0.1308086042],"iteration":392,"passed_time":6.09201341,"remaining_time":9.409292976},
{"learn":[0.1307738065],"iteration":393,"passed_time":6.107264762,"remaining_time":9.393407223},
{"learn":[0.1307431497],"iteration":394,"passed_time":6.12228181,"remaining_time":9.377165811},
{"learn":[0.1307081736],"iteration":395,"passed_time":6.137767868,"remaining_time":9.361645941},
{"learn":[0.1306728103],"iteration":396,"passed_time":6.152572677,"remaining_time":9.345091496},
{"learn":[0.1306426019],"iteration":397,"passed_time":6.169043196,"remaining_time":9.331065336},
{"learn":[0.1306151319],"iteration":398,"passed_time":6.184571287,"remaining_time":9.315607378},
{"learn":[0.1305801444],"iteration":399,"passed_time":6.198591065,"remaining_time":9.297886598},
{"learn":[0.1305471958],"iteration":400,"passed_time":6.213935793,"remaining_time":9.282163441},
{"learn":[0.1305192603],"iteration":401,"passed_time":6.228959355,"remaining_time":9.265964414},
{"learn":[0.1304935248],"iteration":402,"passed_time":6.244484393,"remaining_time":9.250514101},
{"learn":[0.130467147],"iteration":403,"passed_time":6.259886915,"remaining_time":9.234882676},
{"learn":[0.1304261169],"iteration":404,"passed_time":6.275407684,"remaining_time":9.219426104},
{"learn":[0.1303941789],"iteration":405,"passed_time":6.291103317,"remaining_time":9.204225049},
{"learn":[0.1303596697],"iteration":406,"passed_time":6.306936661,"remaining_time":9.189222212},
{"learn":[0.1303376232],"iteration":407,"passed_time":6.321584682,"remaining_time":9.172495421},
{"learn":[0.1303059589],"iteration":408,"passed_time":6.337670018,"remaining_time":9.157855699},
{"learn":[0.1302838187],"iteration":409,"passed_time":6.352483722,"remaining_time":9.141379014},
{"learn":[0.130265549],"iteration":410,"passed_time":6.367896769,"remaining_time":9.125769336},
{"learn":[0.1302335744],"iteration":411,"passed_time":6.382284804,"remaining_time":9.10869773},
{"learn":[0.1302058901],"iteration":412,"passed_time":6.396810243,"remaining_time":9.091834413},
{"learn":[0.1301802817],"iteration":413,"passed_time":6.411906034,"remaining_time":9.075789701},
{"learn":[0.1301550707],"iteration":414,"passed_time":6.427567301,"remaining_time":9.060546678},
{"learn":[0.1301262191],"iteration":415,"passed_time":6.44529131,"remaining_time":9.048197416},
{"learn":[0.1300856213],"iteration":416,"passed_time":6.46067527,"remaining_time":9.032550797},
{"learn":[0.1300762539],"iteration":417,"passed_time":6.475383761,"remaining_time":9.01596495},
{"learn":[0.1300396777],"iteration":418,"passed_time":6.49192987,"remaining_time":9.001936168},
{"learn":[0.1300306072],"iteration":419,"passed_time":6.505604179,"remaining_time":8.98392958},
{"learn":[0.1299989275],"iteration":420,"passed_time":6.521743446,"remaining_time":8.969333623},
{"learn":[0.1299790823],"iteration":421,"passed_time":6.536338659,"remaining_time":8.952615509},
{"learn":[0.1299436265],"iteration":422,"passed_time":6.552905009,"remaining_time":8.938596194},
{"learn":[0.1299086467],"iteration":423,"passed_time":6.568572345,"remaining_time":8.923343563},
{"learn":[0.1298824742],"iteration":424,"passed_time":6.58546567,"remaining_time":8.909747671},
{"learn":[0.1298610083],"iteration":425,"passed_time":6.600461528,"remaining_time":8.893579617},
{"learn":[0.1298319718],"iteration":426,"passed_time":6.614996728,"remaining_time":8.876798888},
{"learn":[0.1297912798],"iteration":427,"passed_time":6.630715546,"remaining_time":8.861610496},
{"learn":[0.1297595712],"iteration":428,"passed_time":6.646901435,"remaining_time":8.847041303},
{"learn":[0.129733675],"iteration":429,"passed_time":6.661701825,"remaining_time":8.830628001},
{"learn":[0.1297037878],"iteration":430,"passed_time":6.677547708,"remaining_time":8.815602426},
{"learn":[0.1296701969],"iteration":431,"passed_time":6.692133794,"remaining_time":8.798916656},
{"learn":[0.1296423033],"iteration":432,"passed_time":6.707322524,"remaining_time":8.783029725},
{"learn":[0.1296135994],"iteration":433,"passed_time":6.723174175,"remaining_time":8.76801056},
{"learn":[0.1295909644],"iteration":434,"passed_time":6.739158991,"remaining_time":8.753160528},
{"learn":[0.1295512713],"iteration":435,"passed_time":6.755427899,"remaining_time":8.738672787},
{"learn":[0.1295247719],"iteration":436,"passed_time":6.770914018,"remaining_time":8.723168404},
{"learn":[0.1295087072],"iteration":437,"passed_time":6.786162165,"remaining_time":8.70735876},
{"learn":[0.1294807186],"iteration":438,"passed_time":6.800739268,"remaining_time":8.690694144},
{"learn":[0.129460713],"iteration":439,"passed_time":6.815931607,"remaining_time":8.674822046},
{"learn":[0.1294247905],"iteration":440,"passed_time":6.831384202,"remaining_time":8.659282923},
{"learn":[0.1294094133],"iteration":441,"passed_time":6.846222831,"remaining_time":8.642969095},
{"learn":[0.1293877081],"iteration":442,"passed_time":6.861831005,"remaining_time":8.627629503},
{"learn":[0.1293536293],"iteration":443,"passed_time":6.87856468,"remaining_time":8.613698113},
{"learn":[0.1293300669],"iteration":444,"passed_time":6.89326108,"remaining_time":8.597213258},
{"learn":[0.1293153272],"iteration":445,"passed_time":6.907448274,"remaining_time":8.58010391},
{"learn":[0.1292796869],"iteration":446,"passed_time":6.924905533,"remaining_time":8.567053153},
{"learn":[0.1292464053],"iteration":447,"passed_time":6.941653433,"remaining_time":8.553108695},
{"learn":[0.1292206811],"iteration":448,"passed_time":6.956696386,"remaining_time":8.537059485},
{"learn":[0.1291908928],"iteration":449,"passed_time":6.973374638,"remaining_time":8.523013446},
{"learn":[0.1291606718],"iteration":450,"passed_time":6.988889715,"remaining_time":8.507539809},
{"learn":[0.1291333939],"iteration":451,"passed_time":7.003670222,"remaining_time":8.491175402},
{"learn":[0.1291181071],"iteration":452,"passed_time":7.019993074,"remaining_time":8.476680379},
{"learn":[0.1291066671],"iteration":453,"passed_time":7.034772286,"remaining_time":8.460320855},
{"learn":[0.1290943566],"iteration":454,"passed_time":7.051187905,"remaining_time":8.445928369},
{"learn":[0.1290679113],"iteration":455,"passed_time":7.066137437,"remaining_time":8.429777995},
{"learn":[0.1290391308],"iteration":456,"passed_time":7.081940441,"remaining_time":8.414646957},
{"learn":[0.1290164962],"iteration":457,"passed_time":7.097109565,"remaining_time":8.398762848},
{"learn":[0.1289926876],"iteration":458,"passed_time":7.11162934,"remaining_time":8.382116498},
{"learn":[0.1289670096],"iteration":459,"passed_time":7.126495129,"remaining_time":8.365885587},
{"learn":[0.1289401231],"iteration":460,"passed_time":7.14156976,"remaining_time":8.349904773},
{"learn":[0.1289137232],"iteration":461,"passed_time":7.157695461,"remaining_time":8.335151858},
{"learn":[0.1288982713],"iteration":462,"passed_time":7.172087095,"remaining_time":8.318381793},
{"learn":[0.1288767516],"iteration":463,"passed_time":7.188658791,"remaining_time":8.304140328},
{"learn":[0.1288513942],"iteration":464,"passed_time":7.203656227,"remaining_time":8.288077595},
{"learn":[0.128843906],"iteration":465,"passed_time":7.218829273,"remaining_time":8.272220668},
{"learn":[0.1288094956],"iteration":466,"passed_time":7.234719416,"remaining_time":8.257185115},
{"learn":[0.1287660605],"iteration":467,"passed_time":7.25031218,"remaining_time":8.241807863},
{"learn":[0.128741986],"iteration":468,"passed_time":7.26503987,"remaining_time":8.225450258},
{"learn":[0.1287279176],"iteration":469,"passed_time":7.280373338,"remaining_time":8.209782701},
{"learn":[0.1286963164],"iteration":470,"passed_time":7.295944987,"remaining_time":8.194384072},
{"learn":[0.1286657565],"iteration":471,"passed_time":7.31146254,"remaining_time":8.178924197},
{"learn":[0.1286488299],"iteration":472,"passed_time":7.32587413,"remaining_time":8.162231853},
{"learn":[0.1286312358],"iteration":473,"passed_time":7.340351892,"remaining_time":8.145622564},
{"learn":[0.1286113644],"iteration":474,"passed_time":7.355239187,"remaining_time":8.129474891},
{"learn":[0.1285795316],"iteration":475,"passed_time":7.370244705,"remaining_time":8.113462659},
{"learn":[0.1285542333],"iteration":476,"passed_time":7.386831556,"remaining_time":8.099188478},
{"learn":[0.1285235382],"iteration":477,"passed_time":7.402343777,"remaining_time":8.08373107},
{"learn":[0.1284909156],"iteration":478,"passed_time":7.417642465,"remaining_time":8.068041178},
{"learn":[0.1284586009],"iteration":479,"passed_time":7.433489416,"remaining_time":8.052946868},
{"learn":[0.1284438108],"iteration":480,"passed_time":7.448672098,"remaining_time":8.03713268},
{"learn":[0.1284141274],"iteration":481,"passed_time":7.464904866,"remaining_time":8.022449628},
{"learn":[0.1283948097],"iteration":482,"passed_time":7.480853037,"remaining_time":8.007455528},
{"learn":[0.128375466],"iteration":483,"passed_time":7.495899435,"remaining_time":7.991496092},
{"learn":[0.1283635671],"iteration":484,"passed_time":7.51160158,"remaining_time":7.976236729},
{"learn":[0.128338705],"iteration":485,"passed_time":7.527043682,"remaining_time":7.96070052},
{"learn":[0.1283038155],"iteration":486,"passed_time":7.542567294,"remaining_time":7.945250558},
{"learn":[0.128287051],"iteration":487,"passed_time":7.557226656,"remaining_time":7.92889354},
{"learn":[0.1282607109],"iteration":488,"passed_time":7.573660849,"remaining_time":7.914398147},
{"learn":[0.128247503],"iteration":489,"passed_time":7.588869138,"remaining_time":7.898618899},
{"learn":[0.1282221495],"iteration":490,"passed_time":7.60405166,"remaining_time":7.882815264},
{"learn":[0.1281973414],"iteration":491,"passed_time":7.619407855,"remaining_time":7.867193476},
{"learn":[0.1281727117],"iteration":492,"passed_time":7.634809141,"remaining_time":7.851619137},
{"learn":[0.1281545631],"iteration":493,"passed_time":7.648684094,"remaining_time":7.834482089},
{"learn":[0.1281453677],"iteration":494,"passed_time":7.664194065,"remaining_time":7.819026268},
{"learn":[0.1281288459],"iteration":495,"passed_time":7.679448611,"remaining_time":7.803310685},
{"learn":[0.1281195748],"iteration":496,"passed_time":7.694805696,"remaining_time":7.787700735},
{"learn":[0.1280884387],"iteration":497,"passed_time":7.7108133,"remaining_time":7.772747543},
{"learn":[0.1280654622],"iteration":498,"passed_time":7.725658003,"remaining_time":7.756622564},
{"learn":[0.1280539779],"iteration":499,"passed_time":7.740321983,"remaining_time":7.740321983},
{"learn":[0.128018331],"iteration":500,"passed_time":7.756223195,"remaining_time":7.725260228},
{"learn":[0.1279866911],"iteration":501,"passed_time":7.772018416,"remaining_time":7.710089982},
{"learn":[0.127963208],"iteration":502,"passed_time":7.786108974,"remaining_time":7.693232923},
{"learn":[0.1279536415],"iteration":503,"passed_time":7.800755536,"remaining_time":7.67693402},
{"learn":[0.1279302527],"iteration":504,"passed_time":7.816967502,"remaining_time":7.662176066},
{"learn":[0.1279220157],"iteration":505,"passed_time":7.831033336,"remaining_time":7.64531713},
{"learn":[0.1279009376],"iteration":506,"passed_time":7.846532735,"remaining_time":7.629863192},
{"learn":[0.1278667404],"iteration":507,"passed_time":7.862518827,"remaining_time":7.614880439},
{"learn":[0.1278349248],"iteration":508,"passed_time":7.877114505,"remaining_time":7.598552499},
{"learn":[0.1278073879],"iteration":509,"passed_time":7.891849842,"remaining_time":7.582365535},
{"learn":[0.1277779808],"iteration":510,"passed_time":7.90685876,"remaining_time":7.566446054},
{"learn":[0.1277491905],"iteration":511,"passed_time":7.923476715,"remaining_time":7.552063744},
{"learn":[0.1277265379],"iteration":512,"passed_time":7.938824914,"remaining_time":7.536467316},
{"learn":[0.1277008657],"iteration":513,"passed_time":7.953438815,"remaining_time":7.520177557},
{"learn":[0.127670151],"iteration":514,"passed_time":7.968523796,"remaining_time":7.504337944},
{"learn":[0.1276559807],"iteration":515,"passed_time":7.98389557,"remaining_time":7.488770263},
{"learn":[0.1276305524],"iteration":516,"passed_time":7.999679011,"remaining_time":7.473587935},
{"learn":[0.1276020176],"iteration":517,"passed_time":8.015661679,"remaining_time":7.458588667},
{"learn":[0.1275698127],"iteration":518,"passed_time":8.031752187,"remaining_time":7.443685553},
{"learn":[0.1275392981],"iteration":519,"passed_time":8.046942798,"remaining_time":7.427947198},
{"learn":[0.1275155116],"iteration":520,"passed_time":8.06188077,"remaining_time":7.411978673},
{"learn":[0.127488456],"iteration":521,"passed_time":8.076556016,"remaining_time":7.395773517},
{"learn":[0.1274606719],"iteration":522,"passed_time":8.091323297,"remaining_time":7.37965815},
{"learn":[0.1274354941],"iteration":523,"passed_time":8.106429341,"remaining_time":7.363855661},
{"learn":[0.1274081679],"iteration":524,"passed_time":8.122039523,"remaining_time":7.348511949},
{"learn":[0.1274010907],"iteration":525,"passed_time":8.136649775,"remaining_time":7.332266147},
{"learn":[0.1273780471],"iteration":526,"passed_time":8.151822982,"remaining_time":7.316531823},
{"learn":[0.127353847],"iteration":527,"passed_time":8.167956108,"remaining_time":7.301657733},
{"learn":[0.1273310361],"iteration":528,"passed_time":8.182954345,"remaining_time":7.285768425},
{"learn":[0.1272935943],"iteration":529,"passed_time":8.201426153,"remaining_time":7.272962815},
{"learn":[0.1272671945],"iteration":530,"passed_time":8.215487018,"remaining_time":7.256239946},
{"learn":[0.1272450014],"iteration":531,"passed_time":8.230548132,"remaining_time":7.240407003},
{"learn":[0.12721443],"iteration":532,"passed_time":8.245840699,"remaining_time":7.22477975},
{"learn":[0.1271848886],"iteration":533,"passed_time":8.261141243,"remaining_time":7.20916071},
{"learn":[0.1271553792],"iteration":534,"passed_time":8.277781754,"remaining_time":7.194707505},
{"learn":[0.1271340703],"iteration":535,"passed_time":8.292265973,"remaining_time":7.178379499},
{"learn":[0.1271138305],"iteration":536,"passed_time":8.307333465,"remaining_time":7.162561256},
{"learn":[0.127090141],"iteration":537,"passed_time":8.32179436,"remaining_time":7.146224896},
{"learn":[0.1270621285],"iteration":538,"passed_time":8.337673313,"remaining_time":7.131108344},
{"learn":[0.1270337872],"iteration":539,"passed_time":8.352920135,"remaining_time":7.115450485},
{"learn":[0.1270068183],"iteration":540,"passed_time":8.368544256,"remaining_time":7.100114258},
{"learn":[0.1269937465],"iteration":541,"passed_time":8.38397453,"remaining_time":7.084613164},
{"learn":[0.1269668423],"iteration":542,"passed_time":8.398971136,"remaining_time":7.068747347},
{"learn":[0.1269391828],"iteration":543,"passed_time":8.414024918,"remaining_time":7.052932652},
{"learn":[0.1269045607],"iteration":544,"passed_time":8.430419785,"remaining_time":7.038240371},
{"learn":[0.1268893635],"iteration":545,"passed_time":8.444883391,"remaining_time":7.021936006},
{"learn":[0.1268689438],"iteration":546,"passed_time":8.460212486,"remaining_time":7.00635513},
{"learn":[0.1268424293],"iteration":547,"passed_time":8.475565232,"remaining_time":6.99079468},
{"learn":[0.126813601],"iteration":548,"passed_time":8.491747559,"remaining_time":6.975916483},
{"learn":[0.1267925297],"iteration":549,"passed_time":8.507961795,"remaining_time":6.96105965},
{"learn":[0.1267748465],"iteration":550,"passed_time":8.524465282,"remaining_time":6.946433596},
{"learn":[0.1267619967],"iteration":551,"passed_time":8.539258437,"remaining_time":6.930412645},
{"learn":[0.1267395357],"iteration":552,"passed_time":8.554653837,"remaining_time":6.914882939},
{"learn":[0.1267037469],"iteration":553,"passed_time":8.578801597,"remaining_time":6.906399842},
{"learn":[0.1266940272],"iteration":554,"passed_time":8.593310137,"remaining_time":6.890131552},
{"learn":[0.1266629393],"iteration":555,"passed_time":8.609336839,"remaining_time":6.875081936},
{"learn":[0.126645192],"iteration":556,"passed_time":8.624616515,"remaining_time":6.859434679},
{"learn":[0.1266233944],"iteration":557,"passed_time":8.639865438,"remaining_time":6.843764379},
{"learn":[0.1265979818],"iteration":558,"passed_time":8.655869388,"remaining_time":6.828691235},
{"learn":[0.1265699792],"iteration":559,"passed_time":8.67063436,"remaining_time":6.812641283},
{"learn":[0.1265557289],"iteration":560,"passed_time":8.686083652,"remaining_time":6.797131414},
{"learn":[0.126529813],"iteration":561,"passed_time":8.701665815,"remaining_time":6.781725315},
{"learn":[0.1265120666],"iteration":562,"passed_time":8.716083242,"remaining_time":6.765414524},
{"learn":[0.1264752139],"iteration":563,"passed_time":8.730992085,"remaining_time":6.749490335},
{"learn":[0.1264641288],"iteration":564,"passed_time":8.745542207,"remaining_time":6.733293558},
{"learn":[0.1264552847],"iteration":565,"passed_time":8.776446715,"remaining_time":6.729642888},
{"learn":[0.126436746],"iteration":566,"passed_time":8.803113049,"remaining_time":6.722659524},
{"learn":[0.1264064076],"iteration":567,"passed_time":8.819161937,"remaining_time":6.707531614},
{"learn":[0.1263874277],"iteration":568,"passed_time":8.833216744,"remaining_time":6.690890012},
{"learn":[0.1263624429],"iteration":569,"passed_time":8.849026773,"remaining_time":6.6755816},
{"learn":[0.1263592153],"iteration":570,"passed_time":8.863451799,"remaining_time":6.659230861},
{"learn":[0.1263320288],"iteration":571,"passed_time":8.878444037,"remaining_time":6.643311272},
{"learn":[0.1262985942],"iteration":572,"passed_time":8.894715429,"remaining_time":6.628348147},
{"learn":[0.1262743395],"iteration":573,"passed_time":8.910985217,"remaining_time":6.613379273},
{"learn":[0.1262275007],"iteration":574,"passed_time":8.927473196,"remaining_time":6.598567145},
{"learn":[0.1262042299],"iteration":575,"passed_time":8.943426462,"remaining_time":6.58335559},
{"learn":[0.1261791107],"iteration":576,"passed_time":8.958539989,"remaining_time":6.56752585},
{"learn":[0.1261592799],"iteration":577,"passed_time":8.973259239,"remaining_time":6.551410725},
{"learn":[0.1261377785],"iteration":578,"passed_time":8.989285395,"remaining_time":6.536250693},
{"learn":[0.1261175494],"iteration":579,"passed_time":9.005547788,"remaining_time":6.521258743},
{"learn":[0.1260953575],"iteration":580,"passed_time":9.020894816,"remaining_time":6.505602285},
{"learn":[0.1260534196],"iteration":581,"passed_time":9.036156179,"remaining_time":6.489885365},
{"learn":[0.1260174529],"iteration":582,"passed_time":9.051889919,"remaining_time":6.474507884},
{"learn":[0.1259897895],"iteration":583,"passed_time":9.067160695,"remaining_time":6.458799399},
{"learn":[0.1259645041],"iteration":584,"passed_time":9.083214425,"remaining_time":6.44364784},
{"learn":[0.1259562184],"iteration":585,"passed_time":9.097385399,"remaining_time":6.427163064},
{"learn":[0.1259405471],"iteration":586,"passed_time":9.112504791,"remaining_time":6.411353456},
{"learn":[0.125914804],"iteration":587,"passed_time":9.128158369,"remaining_time":6.39592049},
{"learn":[0.1258956276],"iteration":588,"passed_time":9.142737071,"remaining_time":6.379736734},
{"learn":[0.1258686913],"iteration":589,"passed_time":9.158434633,"remaining_time":6.364335931},
{"learn":[0.1258309665],"iteration":590,"passed_time":9.174254029,"remaining_time":6.34901844},
{"learn":[0.1258104696],"iteration":591,"passed_time":9.189239819,"remaining_time":6.33312474},
{"learn":[0.125800759],"iteration":592,"passed_time":9.203590982,"remaining_time":6.316798532},
{"learn":[0.1257847348],"iteration":593,"passed_time":9.218404144,"remaining_time":6.300794752},
{"learn":[0.1257474703],"iteration":594,"passed_time":9.233857182,"remaining_time":6.285230519},
{"learn":[0.1257356939],"iteration":595,"passed_time":9.248350837,"remaining_time":6.269016339},
{"learn":[0.125712949],"iteration":596,"passed_time":9.264119673,"remaining_time":6.253668724},
{"learn":[0.1256944447],"iteration":597,"passed_time":9.279835312,"remaining_time":6.238283939},
{"learn":[0.1256659863],"iteration":598,"passed_time":9.295134006,"remaining_time":6.222618926},
{"learn":[0.1256450885],"iteration":599,"passed_time":9.310282367,"remaining_time":6.206854911},
{"learn":[0.1256332716],"iteration":600,"passed_time":9.324717695,"remaining_time":6.190619568},
{"learn":[0.1256197374],"iteration":601,"passed_time":9.339654888,"remaining_time":6.174722002},
{"learn":[0.1255973531],"iteration":602,"passed_time":9.354892701,"remaining_time":6.159025543},
{"learn":[0.1255769562],"iteration":603,"passed_time":9.370160286,"remaining_time":6.143350122},
{"learn":[0.1255629935],"iteration":604,"passed_time":9.385205976,"remaining_time":6.127531175},
{"learn":[0.1255315366],"iteration":605,"passed_time":9.400934387,"remaining_time":6.112158661},
{"learn":[0.1255046655],"iteration":606,"passed_time":9.416611337,"remaining_time":6.096751657},
{"learn":[0.1254748778],"iteration":607,"passed_time":9.43168038,"remaining_time":6.080951824},
{"learn":[0.1254594881],"iteration":608,"passed_time":9.446613505,"remaining_time":6.065067127},
{"learn":[0.1254274416],"iteration":609,"passed_time":9.463180298,"remaining_time":6.050230026},
{"learn":[0.125403194],"iteration":610,"passed_time":9.479078236,"remaining_time":6.03496143},
{"learn":[0.1253689739],"iteration":611,"passed_time":9.498247421,"remaining_time":6.021764705},
{"learn":[0.1253523145],"iteration":612,"passed_time":9.513407348,"remaining_time":6.006017363},
{"learn":[0.1253447591],"iteration":613,"passed_time":9.528244438,"remaining_time":5.990068979},
{"learn":[0.125311055],"iteration":614,"passed_time":9.544959622,"remaining_time":5.975299926},
{"learn":[0.125281129],"iteration":615,"passed_time":9.560758906,"remaining_time":5.959953604},
{"learn":[0.1252563215],"iteration":616,"passed_time":9.576000621,"remaining_time":5.944259705},
{"learn":[0.1252358027],"iteration":617,"passed_time":9.59065456,"remaining_time":5.928203951},
{"learn":[0.1252077892],"iteration":618,"passed_time":9.606498546,"remaining_time":5.912885212},
{"learn":[0.1251737312],"iteration":619,"passed_time":9.621279306,"remaining_time":5.896913123},
{"learn":[0.1251374726],"iteration":620,"passed_time":9.637281968,"remaining_time":5.881690606},
{"learn":[0.1251109568],"iteration":621,"passed_time":9.651797284,"remaining_time":5.865561693},
{"learn":[0.1250960115],"iteration":622,"passed_time":9.66613153,"remaining_time":5.84932839},
{"learn":[0.1250723676],"iteration":623,"passed_time":9.680800746,"remaining_time":5.833303014},
{"learn":[0.1250471598],"iteration":624,"passed_time":9.697085991,"remaining_time":5.818251595},
{"learn":[0.1250234436],"iteration":625,"passed_time":9.71337905,"remaining_time":5.803200902},
{"learn":[0.1250133393],"iteration":626,"passed_time":9.727130066,"remaining_time":5.786633994},
{"learn":[0.1249848509],"iteration":627,"passed_time":9.741600853,"remaining_time":5.770502416},
{"learn":[0.1249774644],"iteration":628,"passed_time":9.755250664,"remaining_time":5.753891886},
{"learn":[0.1249490172],"iteration":629,"passed_time":9.769198311,"remaining_time":5.737465675},
{"learn":[0.1249113683],"iteration":630,"passed_time":9.784493254,"remaining_time":5.721835199},
{"learn":[0.1248960656],"iteration":631,"passed_time":9.799781192,"remaining_time":5.706201707},
{"learn":[0.1248680646],"iteration":632,"passed_time":9.815293795,"remaining_time":5.690699562},
{"learn":[0.1248590635],"iteration":633,"passed_time":9.830254623,"remaining_time":5.674878852},
{"learn":[0.1248380651],"iteration":634,"passed_time":9.845065944,"remaining_time":5.658974913},
{"learn":[0.124817418],"iteration":635,"passed_time":9.86036733,"remaining_time":5.643354887},
{"learn":[0.124800321],"iteration":636,"passed_time":9.874883369,"remaining_time":5.627288325},
{"learn":[0.1247688642],"iteration":637,"passed_time":9.890829251,"remaining_time":5.612037913},
{"learn":[0.1247476454],"iteration":638,"passed_time":9.906820028,"remaining_time":5.596810689},
{"learn":[0.1247272422],"iteration":639,"passed_time":9.921921048,"remaining_time":5.58108059},
{"learn":[0.1247049654],"iteration":640,"passed_time":9.937154236,"remaining_time":5.565426476},
{"learn":[0.1246738303],"iteration":641,"passed_time":9.952643681,"remaining_time":5.54991657},
{"learn":[0.1246636529],"iteration":642,"passed_time":9.967371665,"remaining_time":5.533983957},
{"learn":[0.1246351851],"iteration":643,"passed_time":9.982308276,"remaining_time":5.518170413},
{"learn":[0.1246132248],"iteration":644,"passed_time":9.997979679,"remaining_time":5.502764009},
{"learn":[0.1245965321],"iteration":645,"passed_time":10.01431414,"remaining_time":5.487720131},
{"learn":[0.1245665094],"iteration":646,"passed_time":10.02969929,"remaining_time":5.472154329},
{"learn":[0.1245437519],"iteration":647,"passed_time":10.04451082,"remaining_time":5.456277485},
{"learn":[0.1245214167],"iteration":648,"passed_time":10.06019413,"remaining_time":5.44087541},
{"learn":[0.1244858941],"iteration":649,"passed_time":10.07466542,"remaining_time":5.424819843},
{"learn":[0.1244643404],"iteration":650,"passed_time":10.08956923,"remaining_time":5.409001018},
{"learn":[0.1244439471],"iteration":651,"passed_time":10.10544808,"remaining_time":5.393705417},
{"learn":[0.1244264696],"iteration":652,"passed_time":10.1205267,"remaining_time":5.377982793},
{"learn":[0.1244064055],"iteration":653,"passed_time":10.13692987,"remaining_time":5.362962896},
{"learn":[0.1243803868],"iteration":654,"passed_time":10.15213021,"remaining_time":5.347305224},
{"learn":[0.1243678538],"iteration":655,"passed_time":10.16634725,"remaining_time":5.331133316},
{"learn":[0.1243453297],"iteration":656,"passed_time":10.18309218,"remaining_time":5.316287088},
{"learn":[0.1243186874],"iteration":657,"passed_time":10.19884698,"remaining_time":5.300920466},
{"learn":[0.1242896334],"iteration":658,"passed_time":10.21380602,"remaining_time":5.2851409},
{"learn":[0.1242567739],"iteration":659,"passed_time":10.22907597,"remaining_time":5.269523987},
{"learn":[0.1242439518],"iteration":660,"passed_time":10.24432191,"remaining_time":5.253895808},
{"learn":[0.124220067],"iteration":661,"passed_time":10.2593339,"remaining_time":5.238149331},
{"learn":[0.1241864167],"iteration":662,"passed_time":10.27319966,"remaining_time":5.221822452},
{"learn":[0.1241637396],"iteration":663,"passed_time":10.28837635,"remaining_time":5.206166345},
{"learn":[0.1241365239],"iteration":664,"passed_time":10.30376441,"remaining_time":5.190618159},
{"learn":[0.1241152795],"iteration":665,"passed_time":10.32057452,"remaining_time":5.175783619},
{"learn":[0.1240903011],"iteration":666,"passed_time":10.3351179,"remaining_time":5.159811486},
{"learn":[0.1240586417],"iteration":667,"passed_time":10.35015917,"remaining_time":5.144091085},
{"learn":[0.124035934],"iteration":668,"passed_time":10.36546333,"remaining_time":5.128502783},
{"learn":[0.1240183853],"iteration":669,"passed_time":10.38298964,"remaining_time":5.114009821},
{"learn":[0.1239900745],"iteration":670,"passed_time":10.39859614,"remaining_time":5.098566514},
{"learn":[0.1239741277],"iteration":671,"passed_time":10.41297509,"remaining_time":5.082523555},
{"learn":[0.1239503384],"iteration":672,"passed_time":10.443698,"remaining_time":5.074426813},
{"learn":[0.1239230911],"iteration":673,"passed_time":10.45942464,"remaining_time":5.059009545},
{"learn":[0.1239018451],"iteration":674,"passed_time":10.47449041,"remaining_time":5.043273159},
{"learn":[0.123872654],"iteration":675,"passed_time":10.49015739,"remaining_time":5.027826913},
{"learn":[0.1238555119],"iteration":676,"passed_time":10.50604412,"remaining_time":5.012484862},
{"learn":[0.1238296678],"iteration":677,"passed_time":10.52180327,"remaining_time":4.997080609},
{"learn":[0.1238114097],"iteration":678,"passed_time":10.53712677,"remaining_time":4.981469354},
{"learn":[0.1237810088],"iteration":679,"passed_time":10.55146484,"remaining_time":4.965395217},
{"learn":[0.1237514784],"iteration":680,"passed_time":10.56644417,"remaining_time":4.949626567},
{"learn":[0.1237399112],"iteration":681,"passed_time":10.58077098,"remaining_time":4.933555972},
{"learn":[0.1237283032],"iteration":682,"passed_time":10.5952813,"remaining_time":4.917575656},
{"learn":[0.1237027414],"iteration":683,"passed_time":10.60985779,"remaining_time":4.901630209},
{"learn":[0.1236961055],"iteration":684,"passed_time":10.62363566,"remaining_time":4.88532151},
{"learn":[0.1236668011],"iteration":685,"passed_time":10.6401937,"remaining_time":4.870292741},
{"learn":[0.1236463522],"iteration":686,"passed_time":10.65596329,"remaining_time":4.854900305},
{"learn":[0.1236203153],"iteration":687,"passed_time":10.67117542,"remaining_time":4.83925397},
{"learn":[0.1235949052],"iteration":688,"passed_time":10.6862816,"remaining_time":4.823561069},
{"learn":[0.1235674947],"iteration":689,"passed_time":10.70062798,"remaining_time":4.807528515},
{"learn":[0.1235388366],"iteration":690,"passed_time":10.71556136,"remaining_time":4.791763327},
{"learn":[0.1235186729],"iteration":691,"passed_time":10.73092082,"remaining_time":4.776190191},
{"learn":[0.1234994594],"iteration":692,"passed_time":10.74687319,"remaining_time":4.760880329},
{"learn":[0.1234712661],"iteration":693,"passed_time":10.76213831,"remaining_time":4.745265595},
{"learn":[0.1234424157],"iteration":694,"passed_time":10.77743024,"remaining_time":4.729663629},
{"learn":[0.1234215021],"iteration":695,"passed_time":10.79341049,"remaining_time":4.714363204},
{"learn":[0.1234028872],"iteration":696,"passed_time":10.80982486,"remaining_time":4.699249544},
{"learn":[0.1233755019],"iteration":697,"passed_time":10.82416909,"remaining_time":4.683236481},
{"learn":[0.1233399083],"iteration":698,"passed_time":10.83983574,"remaining_time":4.667797652},
{"learn":[0.123310263],"iteration":699,"passed_time":10.85555374,"remaining_time":4.652380173},
{"learn":[0.123287159],"iteration":700,"passed_time":10.8701105,"remaining_time":4.636466533},
{"learn":[0.1232529685],"iteration":701,"passed_time":10.88562116,"remaining_time":4.62096169},
{"learn":[0.123235708],"iteration":702,"passed_time":10.90258686,"remaining_time":4.606071549},
{"learn":[0.1232207399],"iteration":703,"passed_time":10.91817321,"remaining_time":4.590595556},
{"learn":[0.1231962383],"iteration":704,"passed_time":10.93488004,"remaining_time":4.575588104},
{"learn":[0.1231660333],"iteration":705,"passed_time":10.95104672,"remaining_time":4.560350899},
{"learn":[0.1231331378],"iteration":706,"passed_time":10.9667407,"remaining_time":4.544915171},
{"learn":[0.1231050667],"iteration":707,"passed_time":10.98231217,"remaining_time":4.529428182},
{"learn":[0.1230843305],"iteration":708,"passed_time":10.99933363,"remaining_time":4.514536089},
{"learn":[0.1230778814],"iteration":709,"passed_time":11.01418958,"remaining_time":4.49875349},
{"learn":[0.1230620322],"iteration":710,"passed_time":11.0279966,"remaining_time":4.48254714},
{"learn":[0.1230460989],"iteration":711,"passed_time":11.04330957,"remaining_time":4.466956681},
{"learn":[0.1230230645],"iteration":712,"passed_time":11.05842502,"remaining_time":4.451287493},
{"learn":[0.1230012857],"iteration":713,"passed_time":11.07468828,"remaining_time":4.436079619},
{"learn":[0.1229775213],"iteration":714,"passed_time":11.09161756,"remaining_time":4.421134271},
{"learn":[0.1229508911],"iteration":715,"passed_time":11.10721552,"remaining_time":4.405655317},
{"learn":[0.1229257912],"iteration":716,"passed_time":11.12162658,"remaining_time":4.389707561},
{"learn":[0.1228989861],"iteration":717,"passed_time":11.13682458,"remaining_time":4.374073163},
{"learn":[0.1228754601],"iteration":718,"passed_time":11.15193889,"remaining_time":4.35840727},
{"learn":[0.122869999],"iteration":719,"passed_time":11.16685633,"remaining_time":4.342666351},
{"learn":[0.1228451955],"iteration":720,"passed_time":11.18214732,"remaining_time":4.327072265},
{"learn":[0.1228093901],"iteration":721,"passed_time":11.19807692,"remaining_time":4.311724907},
{"learn":[0.1227904241],"iteration":722,"passed_time":11.21264601,"remaining_time":4.295854697},
{"learn":[0.1227577107],"iteration":723,"passed_time":11.22945422,"remaining_time":4.280841665},
{"learn":[0.1227311627],"iteration":724,"passed_time":11.24527487,"remaining_time":4.265449088},
{"learn":[0.122718042],"iteration":725,"passed_time":11.26119964,"remaining_time":4.25009463},
{"learn":[0.1226993006],"iteration":726,"passed_time":11.27574137,"remaining_time":4.23421925},
{"learn":[0.1226877742],"iteration":727,"passed_time":11.2904494,"remaining_time":4.218409664},
{"learn":[0.1226677902],"iteration":728,"passed_time":11.30477773,"remaining_time":4.202461955},
{"learn":[0.1226366421],"iteration":729,"passed_time":11.31999597,"remaining_time":4.186847824},
{"learn":[0.1226045511],"iteration":730,"passed_time":11.33455815,"remaining_time":4.170993353},
{"learn":[0.1225773003],"iteration":731,"passed_time":11.35005508,"remaining_time":4.155484646},
{"learn":[0.1225524696],"iteration":732,"passed_time":11.36643694,"remaining_time":4.140298313},
{"learn":[0.1225275402],"iteration":733,"passed_time":11.38115498,"remaining_time":4.124505757},
{"learn":[0.1225004287],"iteration":734,"passed_time":11.39705906,"remaining_time":4.109143744},
{"learn":[0.122480239],"iteration":735,"passed_time":11.41170179,"remaining_time":4.093327817},
{"learn":[0.1224595594],"iteration":736,"passed_time":11.42692929,"remaining_time":4.077723748},
{"learn":[0.1224200536],"iteration":737,"passed_time":11.44242524,"remaining_time":4.062216005},
{"learn":[0.1224076489],"iteration":738,"passed_time":11.45688267,"remaining_time":4.046341513},
{"learn":[0.1223834708],"iteration":739,"passed_time":11.47277578,"remaining_time":4.030975275},
{"learn":[0.1223597333],"iteration":740,"passed_time":11.48941462,"remaining_time":4.015868267},
{"learn":[0.1223320179],"iteration":741,"passed_time":11.50535189,"remaining_time":4.000513192},
{"learn":[0.1223055046],"iteration":742,"passed_time":11.52123341,"remaining_time":3.985137263},
{"learn":[0.1222924585],"iteration":743,"passed_time":11.53646212,"remaining_time":3.969535353},
{"learn":[0.1222649967],"iteration":744,"passed_time":11.55268311,"remaining_time":3.954274083},
{"learn":[0.1222490022],"iteration":745,"passed_time":11.56814111,"remaining_time":3.938750457},
{"learn":[0.122233993],"iteration":746,"passed_time":11.58398781,"remaining_time":3.923358657},
{"learn":[0.1222116723],"iteration":747,"passed_time":11.59981708,"remaining_time":3.907959766},
{"learn":[0.1221803291],"iteration":748,"passed_time":11.61488957,"remaining_time":3.892306116},
{"learn":[0.1221711712],"iteration":749,"passed_time":11.63382148,"remaining_time":3.877940494},
{"learn":[0.1221366726],"iteration":750,"passed_time":11.65065834,"remaining_time":3.86286808},
{"learn":[0.1221161033],"iteration":751,"passed_time":11.66541917,"remaining_time":3.847106323},
{"learn":[0.12210282],"iteration":752,"passed_time":11.68064076,"remaining_time":3.831498365},
{"learn":[0.1220805189],"iteration":753,"passed_time":11.69601433,"remaining_time":3.815941014},
{"learn":[0.1220647618],"iteration":754,"passed_time":11.71028949,"remaining_time":3.800027716},
{"learn":[0.1220356847],"iteration":755,"passed_time":11.72618172,"remaining_time":3.784640661},
{"learn":[0.1220119541],"iteration":756,"passed_time":11.74073278,"remaining_time":3.768821751},
{"learn":[0.1220031902],"iteration":757,"passed_time":11.75505485,"remaining_time":3.752933078},
{"learn":[0.1219785031],"iteration":758,"passed_time":11.76960135,"remaining_time":3.737119796},
{"learn":[0.1219513112],"iteration":759,"passed_time":11.78603765,"remaining_time":3.721906628},
{"learn":[0.1219246629],"iteration":760,"passed_time":11.80150668,"remaining_time":3.706386461},
{"learn":[0.121905198],"iteration":761,"passed_time":11.81675013,"remaining_time":3.690795972},
{"learn":[0.121887318],"iteration":762,"passed_time":11.83159441,"remaining_time":3.675082405},
{"learn":[0.121874189],"iteration":763,"passed_time":11.84609313,"remaining_time":3.659264369},
{"learn":[0.1218593349],"iteration":764,"passed_time":11.86048747,"remaining_time":3.643417719},
{"learn":[0.1218307066],"iteration":765,"passed_time":11.8766213,"remaining_time":3.628106245},
{"learn":[0.121813006],"iteration":766,"passed_time":11.8931617,"remaining_time":3.612916137},
{"learn":[0.1217923661],"iteration":767,"passed_time":11.90821152,"remaining_time":3.59727223},
{"learn":[0.1217652395],"iteration":768,"passed_time":11.92448154,"remaining_time":3.581996404},
{"learn":[0.1217396347],"iteration":769,"passed_time":11.9394971,"remaining_time":3.566343289},
{"learn":[0.1217164674],"iteration":770,"passed_time":11.95457188,"remaining_time":3.550709417},
{"learn":[0.1216983345],"iteration":771,"passed_time":11.96902482,"remaining_time":3.53489334},
{"learn":[0.121679586],"iteration":772,"passed_time":11.98470978,"remaining_time":3.519442588},
{"learn":[0.1216641321],"iteration":773,"passed_time":12.00094109,"remaining_time":3.504150758},
{"learn":[0.1216461097],"iteration":774,"passed_time":12.0178155,"remaining_time":3.489043211},
{"learn":[0.1216282168],"iteration":775,"passed_time":12.0331126,"remaining_time":3.473475803},
{"learn":[0.121609862],"iteration":776,"passed_time":12.04790696,"remaining_time":3.457764802},
{"learn":[0.121582043],"iteration":777,"passed_time":12.06271959,"remaining_time":3.442061375},
{"learn":[0.1215537478],"iteration":778,"passed_time":12.07845277,"remaining_time":3.42662139},
{"learn":[0.1215279277],"iteration":779,"passed_time":12.09350809,"remaining_time":3.41098946},
{"learn":[0.1215182809],"iteration":780,"passed_time":12.1079595,"remaining_time":3.395189668},
{"learn":[0.1214952442],"iteration":781,"passed_time":12.12298291,"remaining_time":3.379552779},
{"learn":[0.1214738696],"iteration":782,"passed_time":12.13754362,"remaining_time":3.363789228},
{"learn":[0.1214604313],"iteration":783,"passed_time":12.15251356,"remaining_time":3.348141492},
{"learn":[0.1214304021],"iteration":784,"passed_time":12.16812674,"remaining_time":3.332671654},
{"learn":[0.1214229532],"iteration":785,"passed_time":12.18170631,"remaining_time":3.316647773},
{"learn":[0.1213985909],"iteration":786,"passed_time":12.19746027,"remaining_time":3.301218599},
{"learn":[0.1213700318],"iteration":787,"passed_time":12.21343605,"remaining_time":3.285848279},
{"learn":[0.1213434179],"iteration":788,"passed_time":12.22829325,"remaining_time":3.270177283},
{"learn":[0.1213146063],"iteration":789,"passed_time":12.24431535,"remaining_time":3.254818004},
{"learn":[0.1212836129],"iteration":790,"passed_time":12.26101163,"remaining_time":3.239635183},
{"learn":[0.1212509564],"iteration":791,"passed_time":12.27658839,"remaining_time":3.224154527},
{"learn":[0.1212306747],"iteration":792,"passed_time":12.29102215,"remaining_time":3.208375264},
{"learn":[0.1212082109],"iteration":793,"passed_time":12.30662116,"remaining_time":3.19290171},
{"learn":[0.1211951076],"iteration":794,"passed_time":12.3218669,"remaining_time":3.177336747},
{"learn":[0.1211821994],"iteration":795,"passed_time":12.33747483,"remaining_time":3.161865409},
{"learn":[0.1211529904],"iteration":796,"passed_time":12.35294526,"remaining_time":3.146358705},
{"learn":[0.1211479215],"iteration":797,"passed_time":12.36597219,"remaining_time":3.130233562},
{"learn":[0.1211227368],"iteration":798,"passed_time":12.38221766,"remaining_time":3.114925844},
{"learn":[0.1210999398],"iteration":799,"passed_time":12.39718148,"remaining_time":3.099295371},
{"learn":[0.1210729862],"iteration":800,"passed_time":12.41278749,"remaining_time":3.083826106},
{"learn":[0.1210539323],"iteration":801,"passed_time":12.4282145,"remaining_time":3.068312309},
{"learn":[0.1210281367],"iteration":802,"passed_time":12.44433136,"remaining_time":3.052967967},
{"learn":[0.1210016139],"iteration":803,"passed_time":12.45979126,"remaining_time":3.03746155},
{"learn":[0.1209839642],"iteration":804,"passed_time":12.47687098,"remaining_time":3.022347629},
{"learn":[0.1209599603],"iteration":805,"passed_time":12.49344591,"remaining_time":3.007107329},
{"learn":[0.1209352759],"iteration":806,"passed_time":12.50898435,"remaining_time":2.991615836},
{"learn":[0.1209115682],"iteration":807,"passed_time":12.5252418,"remaining_time":2.976295082},
{"learn":[0.1208895796],"iteration":808,"passed_time":12.54052008,"remaining_time":2.960740835},
{"learn":[0.1208635475],"iteration":809,"passed_time":12.55583274,"remaining_time":2.945195334},
{"learn":[0.1208437296],"iteration":810,"passed_time":12.5709299,"remaining_time":2.929600187},
{"learn":[0.1208240856],"iteration":811,"passed_time":12.58587083,"remaining_time":2.913970093},
{"learn":[0.1208046948],"iteration":812,"passed_time":12.60107982,"remaining_time":2.898403353},
{"learn":[0.1207818154],"iteration":813,"passed_time":12.61825602,"remaining_time":2.883287002},
{"learn":[0.1207559329],"iteration":814,"passed_time":12.63456514,"remaining_time":2.867968773},
{"learn":[0.1207332277],"iteration":815,"passed_time":12.65103641,"remaining_time":2.85268468},
{"learn":[0.1207118963],"iteration":816,"passed_time":12.66629476,"remaining_time":2.837125998},
{"learn":[0.1206869587],"iteration":817,"passed_time":12.68240324,"remaining_time":2.8217572},
{"learn":[0.1206645548],"iteration":818,"passed_time":12.69700121,"remaining_time":2.806052771},
{"learn":[0.1206411825],"iteration":819,"passed_time":12.71158321,"remaining_time":2.790347533},
{"learn":[0.1206140907],"iteration":820,"passed_time":12.72717894,"remaining_time":2.774866054},
{"learn":[0.1205970414],"iteration":821,"passed_time":12.74185391,"remaining_time":2.75918491},
{"learn":[0.1205775178],"iteration":822,"passed_time":12.75756736,"remaining_time":2.743729554},
{"learn":[0.1205452179],"iteration":823,"passed_time":12.77303796,"remaining_time":2.7282217},
{"learn":[0.1205389898],"iteration":824,"passed_time":12.78677875,"remaining_time":2.712347007},
{"learn":[0.1205144073],"iteration":825,"passed_time":12.80212575,"remaining_time":2.696815835},
{"learn":[0.1204977232],"iteration":826,"passed_time":12.8168846,"remaining_time":2.681162076},
{"learn":[0.1204811987],"iteration":827,"passed_time":12.83186923,"remaining_time":2.665557377},
{"learn":[0.1204597223],"iteration":828,"passed_time":12.84926296,"remaining_time":2.650451106},
{"learn":[0.1204429984],"iteration":829,"passed_time":12.86591691,"remaining_time":2.635187802},
{"learn":[0.1204215867],"iteration":830,"passed_time":12.88328754,"remaining_time":2.6200669},
{"learn":[0.1204133334],"iteration":831,"passed_time":12.89881485,"remaining_time":2.604568384},
{"learn":[0.1203970643],"iteration":832,"passed_time":12.91392806,"remaining_time":2.588986779},
{"learn":[0.1203709178],"iteration":833,"passed_time":12.92928896,"remaining_time":2.573455596},
{"learn":[0.1203514562],"iteration":834,"passed_time":12.94530378,"remaining_time":2.55805404},
{"learn":[0.1203233709],"iteration":835,"passed_time":12.96127045,"remaining_time":2.542641571},
{"learn":[0.1203057425],"iteration":836,"passed_time":12.97640655,"remaining_time":2.52706603},
{"learn":[0.1202814504],"iteration":837,"passed_time":12.99222127,"remaining_time":2.511622727},
{"learn":[0.1202626089],"iteration":838,"passed_time":13.00788219,"remaining_time":2.496149026},
{"learn":[0.1202473967],"iteration":839,"passed_time":13.02385968,"remaining_time":2.480735178},
{"learn":[0.120223868],"iteration":840,"passed_time":13.03895462,"remaining_time":2.465153133},
{"learn":[0.1202118534],"iteration":841,"passed_time":13.05474956,"remaining_time":2.449703599},
{"learn":[0.1201879146],"iteration":842,"passed_time":13.06981863,"remaining_time":2.434118061},
{"learn":[0.1201682386],"iteration":843,"passed_time":13.08453064,"remaining_time":2.418467749},
{"learn":[0.1201553778],"iteration":844,"passed_time":13.1000341,"remaining_time":2.402964835},
{"learn":[0.1201338664],"iteration":845,"passed_time":13.11559013,"remaining_time":2.387471489},
{"learn":[0.1201142509],"iteration":846,"passed_time":13.13095715,"remaining_time":2.371943854},
{"learn":[0.1200874834],"iteration":847,"passed_time":13.14680947,"remaining_time":2.356503584},
{"learn":[0.1200649989],"iteration":848,"passed_time":13.16285644,"remaining_time":2.341096964},
{"learn":[0.1200574901],"iteration":849,"passed_time":13.17701166,"remaining_time":2.325354998},
{"learn":[0.1200306798],"iteration":850,"passed_time":13.19252192,"remaining_time":2.309854014},
{"learn":[0.1200090477],"iteration":851,"passed_time":13.20825944,"remaining_time":2.294392485},
{"learn":[0.1199726384],"iteration":852,"passed_time":13.2250769,"remaining_time":2.279116417},
{"learn":[0.1199599025],"iteration":853,"passed_time":13.24007203,"remaining_time":2.263525195},
{"learn":[0.119932916],"iteration":854,"passed_time":13.25496463,"remaining_time":2.247917979},
{"learn":[0.1199115601],"iteration":855,"passed_time":13.271633,"remaining_time":2.23261116},
{"learn":[0.1198891353],"iteration":856,"passed_time":13.28664068,"remaining_time":2.217024057},
{"learn":[0.1198842521],"iteration":857,"passed_time":13.30240574,"remaining_time":2.201563654},
{"learn":[0.1198612082],"iteration":858,"passed_time":13.31767854,"remaining_time":2.18602174},
{"learn":[0.1198495458],"iteration":859,"passed_time":13.33222243,"remaining_time":2.170361791},
{"learn":[0.1198299184],"iteration":860,"passed_time":13.34693671,"remaining_time":2.154731943},
{"learn":[0.1198091558],"iteration":861,"passed_time":13.36336286,"remaining_time":2.139378277},
{"learn":[0.1197934847],"iteration":862,"passed_time":13.37782878,"remaining_time":2.123710942},
{"learn":[0.1197712118],"iteration":863,"passed_time":13.39310381,"remaining_time":2.108173748},
{"learn":[0.1197512952],"iteration":864,"passed_time":13.40900835,"remaining_time":2.092735407},
{"learn":[0.1197235079],"iteration":865,"passed_time":13.42423058,"remaining_time":2.077190413},
{"learn":[0.1197043157],"iteration":866,"passed_time":13.4397516,"remaining_time":2.061691999},
{"learn":[0.1196824316],"iteration":867,"passed_time":13.45452151,"remaining_time":2.046079309},
{"learn":[0.1196657299],"iteration":868,"passed_time":13.47112698,"remaining_time":2.030745264},
{"learn":[0.1196398285],"iteration":869,"passed_time":13.48759199,"remaining_time":2.015387308},
{"learn":[0.1196174764],"iteration":870,"passed_time":13.50415333,"remaining_time":2.000041079},
{"learn":[0.11961374],"iteration":871,"passed_time":13.52342626,"remaining_time":1.985090094},
{"learn":[0.1195969637],"iteration":872,"passed_time":13.5387111,"remaining_time":1.969549038},
{"learn":[0.1195799185],"iteration":873,"passed_time":13.55378129,"remaining_time":1.953977624},
{"learn":[0.1195531451],"iteration":874,"passed_time":13.56985539,"remaining_time":1.93855077},
{"learn":[0.1195156239],"iteration":875,"passed_time":13.58600193,"remaining_time":1.923132693},
{"learn":[0.1194992408],"iteration":876,"passed_time":13.60103679,"remaining_time":1.907557041},
{"learn":[0.1194740118],"iteration":877,"passed_time":13.6161977,"remaining_time":1.892000136},
{"learn":[0.1194502352],"iteration":878,"passed_time":13.63125049,"remaining_time":1.876429248},
{"learn":[0.1194393201],"iteration":879,"passed_time":13.64582772,"remaining_time":1.86079469},
{"learn":[0.1194228037],"iteration":880,"passed_time":13.66075106,"remaining_time":1.845209281},
{"learn":[0.1193945043],"iteration":881,"passed_time":13.67724828,"remaining_time":1.829835938},
{"learn":[0.1193723086],"iteration":882,"passed_time":13.69218273,"remaining_time":1.814252978},
{"learn":[0.1193494562],"iteration":883,"passed_time":13.70708655,"remaining_time":1.798667466},
{"learn":[0.119335953],"iteration":884,"passed_time":13.72323051,"remaining_time":1.783244642},
{"learn":[0.1193212731],"iteration":885,"passed_time":13.73737242,"remaining_time":1.767562591},
{"learn":[0.1193022541],"iteration":886,"passed_time":13.75212172,"remaining_time":1.751961391},
{"learn":[0.1192895638],"iteration":887,"passed_time":13.76698281,"remaining_time":1.73637621},
{"learn":[0.1192675179],"iteration":888,"passed_time":13.78229794,"remaining_time":1.720849349},
{"learn":[0.1192476654],"iteration":889,"passed_time":13.79766431,"remaining_time":1.705329297},
{"learn":[0.119216521],"iteration":890,"passed_time":13.81284873,"remaining_time":1.689787331},
{"learn":[0.1192004183],"iteration":891,"passed_time":13.82760725,"remaining_time":1.6741946},
{"learn":[0.1191821577],"iteration":892,"passed_time":13.84237354,"remaining_time":1.658604668},
{"learn":[0.1191627635],"iteration":893,"passed_time":13.85793411,"remaining_time":1.643110756},
{"learn":[0.1191494589],"iteration":894,"passed_time":13.87499215,"remaining_time":1.627792376},
{"learn":[0.1191185862],"iteration":895,"passed_time":13.89257218,"remaining_time":1.6125307},
{"learn":[0.1190970746],"iteration":896,"passed_time":13.90732332,"remaining_time":1.596939021},
{"learn":[0.1190634313],"iteration":897,"passed_time":13.92345566,"remaining_time":1.581506099},
{"learn":[0.1190329944],"iteration":898,"passed_time":13.93947164,"remaining_time":1.566058549},
{"learn":[0.1190166593],"iteration":899,"passed_time":13.95498985,"remaining_time":1.550554428},
{"learn":[0.1190014402],"iteration":900,"passed_time":13.9701229,"remaining_time":1.535007955},
{"learn":[0.1189908586],"iteration":901,"passed_time":13.98512191,"remaining_time":1.519447835},
{"learn":[0.1189702109],"iteration":902,"passed_time":14.00258978,"remaining_time":1.504154163},
{"learn":[0.1189456533],"iteration":903,"passed_time":14.01976984,"remaining_time":1.488825116},
{"learn":[0.118925074],"iteration":904,"passed_time":14.03463004,"remaining_time":1.473248457},
{"learn":[0.1189063108],"iteration":905,"passed_time":14.0489328,"remaining_time":1.457615544},
{"learn":[0.1188832818],"iteration":906,"passed_time":14.06456328,"remaining_time":1.442121704},
{"learn":[0.1188546801],"iteration":907,"passed_time":14.07985423,"remaining_time":1.426593159},
{"learn":[0.1188331843],"iteration":908,"passed_time":14.09474357,"remaining_time":1.411024934},
{"learn":[0.1188226089],"iteration":909,"passed_time":14.11005107,"remaining_time":1.395499557},
{"learn":[0.1187934206],"iteration":910,"passed_time":14.12596112,"remaining_time":1.380033523},
{"learn":[0.1187760643],"iteration":911,"passed_time":14.14155234,"remaining_time":1.364535752},
{"learn":[0.1187509761],"iteration":912,"passed_time":14.15652632,"remaining_time":1.348978959},
{"learn":[0.118720702],"iteration":913,"passed_time":14.17151785,"remaining_time":1.333425093},
{"learn":[0.1187026033],"iteration":914,"passed_time":14.18587082,"remaining_time":1.317813136},
{"learn":[0.1186795328],"iteration":915,"passed_time":14.20211683,"remaining_time":1.302377526},
{"learn":[0.1186550205],"iteration":916,"passed_time":14.21787777,"remaining_time":1.286896244},
{"learn":[0.1186276236],"iteration":917,"passed_time":14.23257808,"remaining_time":1.271319611},
{"learn":[0.1186049699],"iteration":918,"passed_time":14.2475534,"remaining_time":1.255769124},
{"learn":[0.1185816373],"iteration":919,"passed_time":14.26374343,"remaining_time":1.240325516},
{"learn":[0.118554434],"iteration":920,"passed_time":14.27930438,"remaining_time":1.224826326},
{"learn":[0.11852672],"iteration":921,"passed_time":14.29684713,"remaining_time":1.20949466},
{"learn":[0.1185125454],"iteration":922,"passed_time":14.31207629,"remaining_time":1.193965194},
{"learn":[0.118494501],"iteration":923,"passed_time":14.32739169,"remaining_time":1.178443472},
{"learn":[0.1184616327],"iteration":924,"passed_time":14.34287736,"remaining_time":1.162936002},
{"learn":[0.1184448672],"iteration":925,"passed_time":14.35792638,"remaining_time":1.147393684},
{"learn":[0.1184267431],"iteration":926,"passed_time":14.37237619,"remaining_time":1.131805245},
{"learn":[0.1184221023],"iteration":927,"passed_time":14.38665993,"remaining_time":1.116206374},
{"learn":[0.11839908],"iteration":928,"passed_time":14.40196318,"remaining_time":1.100688252},
{"learn":[0.1183800871],"iteration":929,"passed_time":14.4185847,"remaining_time":1.085269816},
{"learn":[0.1183712046],"iteration":930,"passed_time":14.43296538,"remaining_time":1.069682719},
{"learn":[0.1183625381],"iteration":931,"passed_time":14.44766812,"remaining_time":1.054121708},
{"learn":[0.1183491067],"iteration":932,"passed_time":14.46287991,"remaining_time":1.038599093},
{"learn":[0.1183235372],"iteration":933,"passed_time":14.47984071,"remaining_time":1.023200735},
{"learn":[0.1183063013],"iteration":934,"passed_time":14.49470371,"remaining_time":1.007653199},
{"learn":[0.1182815228],"iteration":935,"passed_time":14.50971858,"remaining_time":0.9921175098},
{"learn":[0.1182686171],"iteration":936,"passed_time":14.52456141,"remaining_time":0.9765713647},
{"learn":[0.1182568778],"iteration":937,"passed_time":14.53889659,"remaining_time":0.9609931646},
{"learn":[0.1182409321],"iteration":938,"passed_time":14.55374271,"remaining_time":0.9454508042},
{"learn":[0.1182224838],"iteration":939,"passed_time":14.56883884,"remaining_time":0.9299258834},
{"learn":[0.1182074001],"iteration":940,"passed_time":14.58466737,"remaining_time":0.9144477945},
{"learn":[0.118186686],"iteration":941,"passed_time":14.60067181,"remaining_time":0.8989797932},
{"learn":[0.1181571247],"iteration":942,"passed_time":14.61617514,"remaining_time":0.8834803636},
{"learn":[0.1181291653],"iteration":943,"passed_time":14.63301775,"remaining_time":0.8680603748},
{"learn":[0.1181217891],"iteration":944,"passed_time":14.64743566,"remaining_time":0.8524962556},
{"learn":[0.1181033979],"iteration":945,"passed_time":14.66438249,"remaining_time":0.8370789159},
{"learn":[0.1180843903],"iteration":946,"passed_time":14.68056424,"remaining_time":0.8216155277},
{"learn":[0.1180600571],"iteration":947,"passed_time":14.69926207,"remaining_time":0.8062886367},
{"learn":[0.11805521],"iteration":948,"passed_time":14.71517556,"remaining_time":0.7908050089},
{"learn":[0.1180385661],"iteration":949,"passed_time":14.73125532,"remaining_time":0.7753292276},
{"learn":[0.1180125388],"iteration":950,"passed_time":14.74784073,"remaining_time":0.7598782289},
{"learn":[0.1179895436],"iteration":951,"passed_time":14.76465131,"remaining_time":0.7444362004},
{"learn":[0.1179639639],"iteration":952,"passed_time":14.7815295,"remaining_time":0.7289946345},
{"learn":[0.1179507453],"iteration":953,"passed_time":14.799637,"remaining_time":0.7136093311},
{"learn":[0.1179229888],"iteration":954,"passed_time":14.82023714,"remaining_time":0.6983357816},
{"learn":[0.1178848972],"iteration":955,"passed_time":14.84037388,"remaining_time":0.6830297603},
{"learn":[0.1178556332],"iteration":956,"passed_time":14.86338862,"remaining_time":0.667842958},
{"learn":[0.1178367673],"iteration":957,"passed_time":14.88293883,"remaining_time":0.6524879239},
{"learn":[0.1178357922],"iteration":958,"passed_time":14.89878897,"remaining_time":0.6369659516},
{"learn":[0.1178174862],"iteration":959,"passed_time":14.91790536,"remaining_time":0.6215793899},
{"learn":[0.1177930012],"iteration":960,"passed_time":14.93659642,"remaining_time":0.6061678046},
{"learn":[0.1177727066],"iteration":961,"passed_time":14.95405408,"remaining_time":0.590700681},
{"learn":[0.1177445356],"iteration":962,"passed_time":14.9710969,"remaining_time":0.5752134842},
{"learn":[0.1177211118],"iteration":963,"passed_time":14.989345,"remaining_time":0.5597680706},
{"learn":[0.1177001009],"iteration":964,"passed_time":15.00758853,"remaining_time":0.5443166826},
{"learn":[0.1176727675],"iteration":965,"passed_time":15.02405354,"remaining_time":0.5287969155},
{"learn":[0.1176532809],"iteration":966,"passed_time":15.04236066,"remaining_time":0.5133380576},
{"learn":[0.1176235611],"iteration":967,"passed_time":15.06077516,"remaining_time":0.4978768648},
{"learn":[0.1176037986],"iteration":968,"passed_time":15.07928614,"remaining_time":0.4824126628},
{"learn":[0.1175847075],"iteration":969,"passed_time":15.09699837,"remaining_time":0.4669174754},
{"learn":[0.1175689596],"iteration":970,"passed_time":15.11396213,"remaining_time":0.4513953675},
{"learn":[0.1175478372],"iteration":971,"passed_time":15.13191815,"remaining_time":0.4358988767},
{"learn":[0.1175292428],"iteration":972,"passed_time":15.14887679,"remaining_time":0.4203696539},
{"learn":[0.1175174225],"iteration":973,"passed_time":15.16533687,"remaining_time":0.4048241875},
{"learn":[0.1174890067],"iteration":974,"passed_time":15.18207566,"remaining_time":0.3892839914},
{"learn":[0.1174752808],"iteration":975,"passed_time":15.19881481,"remaining_time":0.3737413479},
{"learn":[0.1174563885],"iteration":976,"passed_time":15.21454602,"remaining_time":0.3581725266},
{"learn":[0.1174315408],"iteration":977,"passed_time":15.23003418,"remaining_time":0.342597906},
{"learn":[0.1174228407],"iteration":978,"passed_time":15.24450901,"remaining_time":0.3270017255},
{"learn":[0.1173980126],"iteration":979,"passed_time":15.26067942,"remaining_time":0.3114424372},
{"learn":[0.1173773898],"iteration":980,"passed_time":15.27712008,"remaining_time":0.2958871371},
{"learn":[0.117357738],"iteration":981,"passed_time":15.29330665,"remaining_time":0.2803253764},
{"learn":[0.1173354495],"iteration":982,"passed_time":15.30860264,"remaining_time":0.2647469429},
{"learn":[0.117315131],"iteration":983,"passed_time":15.32417935,"remaining_time":0.2491736479},
{"learn":[0.1172997828],"iteration":984,"passed_time":15.33849313,"remaining_time":0.2335811136},
{"learn":[0.1172902435],"iteration":985,"passed_time":15.35325016,"remaining_time":0.2179974667},
{"learn":[0.1172835014],"iteration":986,"passed_time":15.36810989,"remaining_time":0.2024168476},
{"learn":[0.1172604784],"iteration":987,"passed_time":15.38274737,"remaining_time":0.1868349882},
{"learn":[0.1172424099],"iteration":988,"passed_time":15.398646,"remaining_time":0.1712690657},
{"learn":[0.1172223035],"iteration":989,"passed_time":15.41511887,"remaining_time":0.1557082715},
{"learn":[0.117219595],"iteration":990,"passed_time":15.42971139,"remaining_time":0.1401285596},
{"learn":[0.1171996013],"iteration":991,"passed_time":15.44628859,"remaining_time":0.1245668434},
{"learn":[0.117161655],"iteration":992,"passed_time":15.46369856,"remaining_time":0.1090089526},
{"learn":[0.1171519985],"iteration":993,"passed_time":15.47971555,"remaining_time":0.09343892683},
{"learn":[0.1171354569],"iteration":994,"passed_time":15.49555608,"remaining_time":0.07786711596},
{"learn":[0.1171081871],"iteration":995,"passed_time":15.51177063,"remaining_time":0.06229626761},
{"learn":[0.117101582],"iteration":996,"passed_time":15.52796657,"remaining_time":0.04672407191},
{"learn":[0.117078951],"iteration":997,"passed_time":15.54286267,"remaining_time":0.03114802137},
{"learn":[0.1170579121],"iteration":998,"passed_time":15.55922831,"remaining_time":0.01557480311},
{"learn":[0.1170324496],"iteration":999,"passed_time":15.57441462,"remaining_time":0}
]}